Workbook

Sheet Core 8-Component Selection
A1: CORE 101 — 8-Component Literature Selection (for Progress Report)
A2: Mapped from your Annotated Bibliography's 8 sections (Kinetic Models, Transport-Deposition, Inhibitor Modeling, ML-Tendency, ML-Thermodynamics, ML-Thickness, Similar Applications, Pipe Monitoring). Selected from the 411 title/abstract-included records by: R-tag priority, then Citation Velocity, then component-match confidence, quota-capped per component to land at ~90-100 total while preserving full 8-pillar coverage.
A4: Component | B4: Selected
A5: 1. Kinetic Models | B5: 15
A6: 2. Transport-Deposition Approaches | B6: 15
A7: 3. Inhibitor Modeling | B7: 22
A8: 4. ML - Scale Tendency | B8: 15
A9: 5. ML - Scale Thermodynamics | B9: 12
A10: 6. ML - Scale Thickness (Sensor-Based) | B10: 9
A11: 7. Similar Applications (Adjacent Domains) | B11: 5
A12: 8. Pipe Monitoring (Structural/Deposit Sensing) | B12: 8
A13: TOTAL | B13: 101
A16: Component | B16: Title | C16: Authors | D16: Year | E16: Venue | F16: DOI | G16: Tag | H16: Citations | I16: Cit. Velocity
A17: 1. Kinetic Models | B17: A review of iron carbonate (FeCO3) formation in the oil and gas industry | C17: Barker, R; Burkle, D; Charpentier, T; Thompson, H; Neville, A | D17: 2018 | E17: CORROSION SCIENCE | F17: 10.1016/j.corsci.2018.07.021 | G17: R | H17: 196 | I17: 21.78
A18: 1. Kinetic Models | B18: Examining the factors that impact the formation of barite scale in water injection operations: experimental study and quantification of scale formation | C18: Hussein M.F.; Mubarak M.F.; Al-Sirhani A.M.; Hosny R. | D18: 2024 | E18: Discover Applied Sciences | F18: 10.1007/s42452-024-06176-7 | G18: R | H18: 64 | I18: 21.33
A19: 1. Kinetic Models | B19: Surface inorganic scale formation in oil and gas industry: As adhesion and deposition processes | C19: Vazirian M.M.; Charpentier T.V.J.; de Oliveira Penna M.; Neville A. | D19: 2016 | E19: Journal of Petroleum Science and Engineering | F19: 10.1016/j.petrol.2015.11.005 | G19: R | H19: 148 | I19: 13.45
A20: 1. Kinetic Models | B20: The early stages of FeCO3 scale formation kinetics in CO2 corrosion | C20: De Motte R.A.; Barker R.; Burkle D.; Vargas S.M.; Neville A. | D20: 2018 | E20: Materials Chemistry and Physics | F20: 10.1016/j.matchemphys.2018.04.077 | G20: R | H20: 102 | I20: 11.33
A21: 1. Kinetic Models | B21: In situ SR-XRD study of FeCO3 precipitation kinetics onto carbon steel in CO2-containing environments: The influence of brine pH | C21: Burkle, D; De Motte, R; Taleb, W; Kleppe, A; Comyn, T; Vargas, SM; Neville, A; Barker, R | D21: 2017 | E21: ELECTROCHIMICA ACTA | F21: 10.1016/j.electacta.2017.09.138 | G21: R | H21: 70 | I21: 7
A22: 1. Kinetic Models | B22: Experimental and modelling approach to investigate the mechanisms of formation damage due to calcium carbonate precipitation in carbonate reservoirs | C22: Qazvini S.; Golkari A.; Azdarpour A.; Santos R.M.; Safavi M.S.; Norouzpour M. | D22: 2021 | E22: Journal of Petroleum Science and Engineering | F22: 10.1016/j.petrol.2021.108801 | G22: R | H22: 36 | I22: 6
A23: 1. Kinetic Models | B23: Kinetics study of barium sulphate surface scaling and inhibition with a once-through flow system | C23: Bukuaghangin O.; Sanni O.; Kapur N.; Huggan M.; Neville A.; Charpentier T. | D23: 2016 | E23: Journal of Petroleum Science and Engineering | F23: 10.1016/j.petrol.2016.09.035 | G23: R | H23: 47 | I23: 4.27
A24: 1. Kinetic Models | B24: Preparation and Performance Study of Microemulsion Acid for Comprehensive Plugging Removal in Carbonate Reservoir | C24: Wang Y.; Zhou F.; Zou Y.; Wang Z.; Wang Y. | D24: 2023 | E24: Molecules | F24: 10.3390/molecules28145606 | G24: R | H24: 16 | I24: 4
A25: 1. Kinetic Models | B25: Fast evaluation of inhibitors for calcium carbonate scale based on pH continuous measurements in jar test at high salinity condition | C25: Sousa, MFB; Signorelli, F; Bertran, CA | D25: 2016 | E25: JOURNAL OF PETROLEUM SCIENCE AND ENGINEERING | F25: 10.1016/j.petrol.2016.09.007 | G25: R | H25: 43 | I25: 3.91
A26: 1. Kinetic Models | B26: A comprehensive study of impact of solid particles on scaling formation and inhibition in oilfield water | C26: Zhang H.; Dong M.; Ni J.; Li B.; Mao H.; Chen G.; Tang Y. | D26: 2025 | E26: Desalination and Water Treatment | F26: 10.1016/j.dwt.2025.101331 | G26: R | H26: 6 | I26: 3
A27: 1. Kinetic Models | B27: Real-time monitoring of electrochemically induced calcium carbonate depositions: Kinetics and mechanisms | C27: Liu Z.; Onay H.; Guo F.; Lv Q.; Sudhölter E.J.R. | D27: 2021 | E27: Electrochimica Acta | F27: 10.1016/j.electacta.2021.137719 | G27: R | H27: 17 | I27: 2.83
A28: 1. Kinetic Models | B28: Kinetics of Barium Sulfate Deposition and Crystallization Process in the Flowing Tube | C28: Lu A.Y.-T.; Harouaka K.; Paudyal S.; Ko S.; Dai C.; Gao S.; Deng G.; Zhao Y.; Wang X.; Mateen S.; Kan A.T.; Tomson M. | D28: 2020 | E28: Industrial and Engineering Chemistry Research | F28: 10.1021/acs.iecr.0c00112 | G28: R | H28: 19 | I28: 2.71
... A42: 2. Transport-Deposition Approaches | B42: On the hydrodynamic aspects of the carbonate scale formation process in high flow rate wells | C42: Maciel R.S.; Cosmo R.P.; Maciel F.S.; Pereira F.A.R.; Ribeiro D.C.; Aldeia S.W.; Martins A.L. | D42: 2017 | E42: OTC Brasil 2017 | F42: 10.4043/28106-ms | G42: R | H42: 5 | I42: 0.5
A43: 2. Transport-Deposition Approaches | B43: Modelling CaCO3 scale in CO2 water alternating gas CO2-WAG processes | C43: Silva D.; Sorbie K.S.; Mackay E.J. | D43: 2016 | E43: Society of Petroleum Engineers - SPE International Oilfield Scale Conference and Exhibition | G43: R | H43: 5 | I43: 0.45
A44: 2. Transport-Deposition Approaches | B44: Methodology to Evaluate Calcite Scale Inhibitors Under Turbulent Flow for Subsea Oilfield Production Applications | C44: Pimentel D.; Kan A.; Ye Y.; Wang X.; Reiss A.; Deng G.; Shen Y.-Y.; Leschied C.; Yao T.; Tomson M. | D44: 2024 | E44: Society of Petroleum Engineers - SPE Oilfield Scale Symposium, OSS 2024 | F44: 10.2118/218736-MS | G44: R | H44: 1 | I44: 0.33
A45: 2. Transport-Deposition Approaches | B45: Strategic Scale Mitigation for Oil Wells with a Low Basic Sediment and Water | C45: Benkhaled M.; Tort F.; Baraka-Lokmane S.; Fretard D.; Lesage N. | D45: 2024 | E45: Society of Petroleum Engineers - SPE Oilfield Scale Symposium, OSS 2024 | F45: 10.2118/218702-MS | G45: R | H45: 1 | I45: 0.33
A46: 2. Transport-Deposition Approaches | B46: Comprehensive Modeling of Scale Deposition by Use of a Coupled Geochemical and Compositional Wellbore Simulator | C46: Ali Abouie; Aboulghasem Kazemi Korrani; Mahdy Shirdel; Kamy Sepehrnoori | D46: 2017 | E46: SPE Journal | F46: 10.2118/185942-pa | G46: R | H46: 23 | I46: 2.3
A47: 3. Inhibitor Modeling | B47: Mineral Reactions in Shale Gas Reservoirs: Barite Scale Formation from Reusing Produced Water As Hydraulic Fracturing Fluid | C47: Paukert Vankeuren A.N.; Hakala J.A.; Jarvis K.; Moore J.E. | D47: 2017 | E47: Environmental Science and Technology | F47: 10.1021/acs.est.7b01979 | G47: R | H47: 149 | I47: 14.9
A48: 3. Inhibitor Modeling | B48: Performance evaluation of hybrid polymer-phosphonate scale inhibitors in oilfield water flooding operations | C48: Khormali A.; Ahmadi S.; Kazemzadeh Y. | D48: 2026 | E48: Petroleum Research | F48: 10.1016/j.ptlrs.2026.01.014 | G48: R | H48: 11 | I48: 11
A49: 3. Inhibitor Modeling | B49: Environmentally Friendly Phosphonated Polyetheramine Scale Inhibitors - Excellent Calcium Compatibility for Oilfield Applications | C49: Mady M.F.; Bayat P.; Kelland M.A. | D49: 2020 | E49: Industrial and Engineering Chemistry Research | F49: 10.1021/acs.iecr.0c01636 | G49: R | H49: 73 | I49: 10.43
A50: 3. Inhibitor Modeling | B50: Anti-corrosion, antiscalant and anti-microbial performance of some synthesized trimeric cationic imidazolium salts in oilfield applications | C50: Shaban M.M.; Negm N.A.; Farag R.K.; Fadda A.A.; Gomaa A.E.; Farag A.A.; Migahed M.A. | D50: 2022 | E50: Journal of Molecular Liquids | F50: 10.1016/j.molliq.2022.118610 | G50: R | H50: 50 | I50: 10
A51: 3. Inhibitor Modeling | B51: Evaluation of different polymeric scale inhibitors for oilfield application | C51: Bisatto R.; Picoli V.M.; Petzhold C.L. | D51: 2022 | E51: Journal of Petroleum Science and Engineering | F51: 10.1016/j.petrol.2022.110331 | G51: R | H51: 48 | I51: 9.6
A52: 3. Inhibitor Modeling | B52: Increasing efficiency of calcium sulfate scale prevention using a new mixture of phosphonate scale inhibitors during waterflooding | C52: Khormali A.; Sharifov A.R.; Torba D.I. | D52: 2018 | E52: Journal of Petroleum Science and Engineering | F52: 10.1016/j.petrol.2018.01.055 | G52: R | H52: 85 | I52: 9.44
A53: 3. Inhibitor Modeling | B53: Prediction of barium sulfate precipitation in dynamic tube blocking tests and its inhibition for waterflooding application using response surface methodology | C53: Khormali A.; Ahmadi S. | D53: 2023 | E53: Journal of Petroleum Exploration and Production Technology | F53: 10.1007/s13202-023-01679-2 | G53: R | H53: 37 | I53: 9.25
A54: 3. Inhibitor Modeling | B54: A review: the utilization potency of biopolymer as an eco-friendly scale inhibitors | C54: Husna, UZ; Elraies, KA; Shuhili, JABM; Elryes, AA | D54: 2022 | E54: JOURNAL OF PETROLEUM EXPLORATION AND PRODUCTION TECHNOLOGY | F54: 10.1007/s13202-021-01370-4 | G54: R | H54: 40 | I54: 8
A55: 3. Inhibitor Modeling | B55: Increasing inhibition performance of simultaneous precipitation of calcium and strontium sulfate scales using a new inhibitor — Laboratory and field application | C55: Khormali A.; Bahlakeh G.; Struchkov I.; Kazemzadeh Y. | D55: 2021 | E55: Journal of Petroleum Science and Engineering | F55: 10.1016/j.petrol.2021.108589 | G55: R | H55: 41 | I55: 6.83
... A82: 4. ML - Scale Tendency | B82: Scale Build-Up Prediction of FeS and FeCO3 in Gas Production Pipes | C82: Santoso, RK; Rahmawati, SD; Gadesa, A; Wahyuningrum, D | D82: 2017 | E82: INTERNATIONAL CONFERENCE ON ENERGY SCIENCES (ICES 2016) | F82: 10.1088/1742-6596/877/1/012029 | G82: R | H82: 3 | I82: 0.3
A83: 4. ML - Scale Tendency | B83: Advances in understanding the scaling potential for thermal wells: A mechanistic study | C83: Habibi A.; Fensky C.; Roostaei M.; Mahmoudi M.; Fattahpour V.; Zeng H.; Sadrzadeh M. | D83: 2020 | E83: Society of Petroleum Engineers - SPE Canada Heavy Oil Conference 2020, CHOC 2020 | G83: R | H83: 2 | I83: 0.29
A84: 5. ML - Scale Thermodynamics | B84: Effect of salinity and ion type on formation damage due to inorganic scale deposition and introducing optimum salinity | C84: Ghasemian J.; Riahi S.; Ayatollahi S.; Mokhtari R. | D84: 2019 | E84: Journal of Petroleum Science and Engineering | F84: 10.1016/j.petrol.2019.02.019 | G84: R | H84: 60 | I84: 7.5
A85: 5. ML - Scale Thermodynamics | B85: Iron sulfide scale management in High-H2S and -CO2 carbonate reservoirs | C85: Verri G.; Sorbie K.S.; Singleton M.A.; Hinrichsen C.; Wang Q.; Chang F.F.; Ramachandran S. | D85: 2017 | E85: SPE Production and Operations | F85: 10.2118/179871-pa | G85: R | H85: 21 | I85: 2.1
A86: 5. ML - Scale Thermodynamics | B86: Coupling Well Log Data with Chemical Thermodynamic Modeling for Predicting Mineral Precipitation Along the Wellbore Depth Profile | C86: Tuhami M.; Al-Saleem H.; Alshammari S.; Rafie M.; Alsaud M.A. | D86: 2025 | E86: Society of Petroleum Engineers - SPE Advances in Integrated Reservoir Modelling and Field Development Conference and Exhibition, RCSC 2025 | F86: 10.2118/225407-MS | G86: R | H86: 4 | I86: 2
A87: 5. ML - Scale Thermodynamics | B87: Advanced Scale Removal in a Non-Injective Well Using Custom Jetting Tools and Chelating Chemistry | C87: Mohamed M.A.A.; Al Bloushi M.A.; Albloushi M.J.; Al Janahi M.I.; Alali M.H.; Mohamed M.E.; Alqaydi S.; Sidharth P.; Varshney M.; Grutters M.; Maheshwari Y.K.; Akhtar M.M.; Ahmad B.; Halverson S.; Ramy C. | D87: 2025 | E87: Society of Petroleum Engineers - ADIPEC 2025 | F87: 10.2118/230084-MS | G87: R | H87: 4 | I87: 2
A88: 5. ML - Scale Thermodynamics | B88: Comprehensive thermodynamic modeling of saline water with electrolyte NRTL model: A study on aqueous Ba2+-Na+-Cl--Sa42- quaternary system | C88: Honarparvar, S; Saravi, SH; Reible, D; Chen, CC | D88: 2017 | E88: FLUID PHASE EQUILIBRIA | F88: 10.1016/j.fluid.2017.05.016 | G88: R | H88: 18 | I88: 1.8
A89: 5. ML - Scale Thermodynamics | B89: Minimizing the Barite Scale in Carbonate Formations during the Filter Cake Removal Process | C89: Al Jaberi, J; Ahmed, A; Bageri, B; Elsayed, M; Mahmoud, M; Patil, S; Al-Garadi, K; Barri, A | D89: 2022 | E89: ACS OMEGA | F89: 10.1021/acsomega.2c01339 | G89: R | H89: 9 | I89: 1.8
A90: 5. ML - Scale Thermodynamics | B90: Chelating Chemicals: A Solution to End the Battle with Calcium Sulfate Scale | C90: Alotaibi F.; Almubarak T.; Alhamad L.; Al Moajil A. | D90: 2023 | E90: SPE Middle East Oil and Gas Show and Conference, MEOS, Proceedings | F90: 10.2118/213502-MS | G90: R | H90: 6 | I90: 1.5
A91: 5. ML - Scale Thermodynamics | B91: Impact of High Calcium Concentrations on Barite Scale Prediction Under High Temperature and High Pressure Conditions | C91: Shen Y.-Y.; Deng G.; Wang X.; Ye Y.; Reiss A.; Yao X.; Pimentel D.; Leschied C.; Kan A.T.; Tomson M.B. | D91: 2024 | E91: Society of Petroleum Engineers - SPE Oilfield Scale Symposium, OSS 2024 | F91: 10.2118/218707-MS | G91: R | H91: 3 | I91: 1
A92: 5. ML - Scale Thermodynamics | B92: Iron sulphide scale management in high H2S and CO2 carbonate reservoirs | C92: Verri G.; Sorbie K.S.; Singleton M.A.; Hinrichsen C.; Wang Q.; Chang F.F.; Ramachandran S. | D92: 2016 | E92: Society of Petroleum Engineers - SPE International Oilfield Scale Conference and Exhibition | G92: R | H92: 11 | I92: 1
A93: 5. ML - Scale Thermodynamics | B93: Numerical Simulation of Scale Formation for Injection-Production Units in Oil Reservoirs | C93: Li, NY; Kang, J; Zhang, HT; Tao, WD; Ren, Y | D93: 2019 | E93: ARABIAN JOURNAL FOR SCIENCE AND ENGINEERING | F93: 10.1007/s13369-019-03975-8 | G93: R | H93: 4 | I93: 0.5
A94: 5. ML - Scale Thermodynamics | B94: Mineral solubility measurement and prediction under high pressure, high temperature reservoir conditions | C94: Goodwin N.; May M.; Wilson S.; Graham G. | D94: 2020 | E94: Proceedings - SPE International Symposium on Formation Damage Control | G94: R | H94: 1 | I94: 0.14
A95: 5. ML - Scale Thermodynamics | B95: Study on deposit formation model in sulfide-containing natural gas environment | C95: Yongliang L.; Zhidong O.; Hongda D.; Zewei Z.; Yunfan Z.; Jian L. | D95: 2023 | E95: Journal of Petroleum Exploration and Production Technology | F95: 10.1007/s13202-022-01594-y | G95: R | H95: 0 | I95: 0
A96: 6. ML - Scale Thickness (Sensor-Based) | B96: Calculation of volume fractions regardless scale deposition in the oil industry pipelines using feed-forward multilayer perceptron artificial neural network and MCNP6 code | C96: Salgado, CM; Dam, RSF; Puertas, EJA; Salgado, WL | D96: 2022 | E96: APPLIED RADIATION AND ISOTOPES | F96: 10.1016/j.apradiso.2022.110215 | G96: R | H96: 19 | I96: 3.8
A97: 6. ML - Scale Thickness (Sensor-Based) | B97: Inorganic scale thickness prediction in oil pipelines by gamma-ray attenuation and artificial neural network | C97: Teixeira, TP; Salgado, CM; Dam, RSD; Salgado, WL | D97: 2018 | E97: APPLIED RADIATION AND ISOTOPES | F97: 10.1016/j.apradiso.2018.08.008 | G97: R | H97: 15 | I97: 1.67
A98: 6. ML - Scale Thickness (Sensor-Based) | B98: Application of deep neural network and gamma-ray scattering in eccentric scale calculation regardless of the fluids volume fraction inside a pipeline | C98: Dam, RSD; Salgado, WL; Schirru, R; Salgado, CM | D98: 2022 | E98: APPLIED RADIATION AND ISOTOPES | F98: 10.1016/j.apradiso.2022.110353 | G98: R | H98: 6 | I98: 1.2
A99: 6. ML - Scale Thickness (Sensor-Based) | B99: Case study: Barium sulfate scale removal by dynamic underbalance | C99: Mahmud W.M.; Ermila M. | D99: 2020 | E99: Proceedings - SPE International Symposium on Formation Damage Control | F99: 10.2118/199232-ms | G99: R | H99: 2 | I99: 0.29
A100: 6. ML - Scale Thickness (Sensor-Based) | B100: Feasibility assessment of calcium carbonate scale thickness and volume fraction estimation in three-phase flow using neutron activation analysis and deep neural networks | C100: Dam, RSD; Salgado, WL; Salgado, CM | D100: 2026 | E100: APPLIED RADIATION AND ISOTOPES | F100: 10.1016/j.apradiso.2026.112821 | G100: R | H100: 0 | I100: 0
A101: 6. ML - Scale Thickness (Sensor-Based) | B101: Method of Ultrasonic Inspection for Scale Thickness in Titanium Alloy Seawater Pipelines | C101: Y. Huang; Z. Lin; E. Yan; Q. Pan; L. Xu; R. Liao; J. Sun | D101: 2026 | E101: 2026 IEEE International Conference on Mechatronics and Automation (ICMA) | F101: 10.1109/ICMA69663.2026.11647573 | G101: R | H101: 0 | I101: 0
A102: 6. ML - Scale Thickness (Sensor-Based) | B102: Electro-Hydraulic Pulsing Used to Clear Barium Sulfate Scale and Improve Production on a Multi-Well Campaign | C102: Cubas D.; Kamaraj K.; Perri M.; McKenzie C.; Fisher J. | D102: 2026 | E102: Society of Petroleum Engineers - SPE/ICoTA Well Intervention Conference and Exhibition, CTWI 2026 | F102: 10.2118/231343-MS | G102: R | H102: 0 | I102: 0
A103: 6. ML - Scale Thickness (Sensor-Based) | B103: Effect of Inorganic Scales on Water Injection Performance: Quantitative Analysis, Mitigation, and Prevention Measures | C103: Durmagambetov B.; Abdrazakov D. | D103: 2025 | E103: Society of Petroleum Engineers - ADIPEC 2025 | F103: 10.2118/230006-MS | G103: R | H103: 0 | I103: 0
A104: 6. ML - Scale Thickness (Sensor-Based) | B104: Non-Contact Measurement of Non-Metallic Scale Thickness on the Back Side of Ferromagnetic Materials Using Electromagnetic Force–Induced Vibration | C104: M. Tohara; K. Okuma; Y. Gotoh | D104: 2026 | E104: IEEE Transactions on Magnetics | F104: 10.1109/TMAG.2026.3695830 | G104: M | H104: 0 | I104: 0
A105: 7. Similar Applications (Adjacent Domains) | B105: Use of rice straw-based biochar for batch sorption of barium/strontium from saline water: Protection against scale formation in petroleum/desalination industries | C105: Younis S.A.; El-Salamony R.A.; Tsang Y.F.; Kim K.-H. | D105: 2020 | E105: Journal of Cleaner Production | F105: 10.1016/j.jclepro.2019.119442 | G105: R | H105: 67 | I105: 9.57
A106: 7. Similar Applications (Adjacent Domains) | B106: Acoustic Anti-Scaling Technology for Sustainable Scaling Prevention in the Oil and Gas Industry | C106: Al Munif E.H.; Alhamad L.A.; Almubarak T.A. | D106: 2023 | E106: Society of Petroleum Engineers - ADIPEC, ADIP 2023 | F106: 10.2118/216280-MS | G106: R | H106: 3 | I106: 0.75
A107: 7. Similar Applications (Adjacent Domains) | B107: Comparison of indices for scaling and corrosion tendency of groundwater: Case study of unconfined aquifer from Mahoba District, U.P. State | C107: Mankikar T.Y. | D107: 2021 | E107: Applied Water Science | F107: 10.1007/s13201-021-01423-3 | G107: M | H107: 20 | I107: 3.33
A108: 7. Similar Applications (Adjacent Domains) | B108: ASSESSMENT OF OF QUALITY AND POTENTIAL OF SCALE FORMATION AND CORROSIVITY OF DRINKING WATER SUPPLIED FROM DISI TO AMMAN, JORDAN | C108: AlShamaileh, E; AlRawajfeh, A; AlMa'abrah, A | D108: 2017 | E108: FRESENIUS ENVIRONMENTAL BULLETIN | G108: M | H108: 7 | I108: 0.7
A109: 7. Similar Applications (Adjacent Domains) | B109: Evaluation of Water Quality Influence on Power Plant Cooling System | C109: J. Boguniewicz-Zablocka; P. Danisz; R. Gono | D109: 2022 | E109: 2022 22nd International Scientific Conference on Electric Power Engineering (EPE) | F109: 10.1109/EPE54603.2022.9814150 | G109: M | H109: 0 | I109: 0
A110: 8. Pipe Monitoring (Structural/Deposit Sensing) | B110: Study on removing calcium carbonate plug from near wellbore by high-power ultrasonic treatment | C110: Zhang X.; Zang C.; Ma H.; Wang Z. | D110: 2020 | E110: Ultrasonics Sonochemistry | F110: 10.1016/j.ultsonch.2019.03.006 | G110: R | H110: 61 | I110: 8.71
A111: 8. Pipe Monitoring (Structural/Deposit Sensing) | B111: Ultrasound based technology for removal of scale from downhole production tubing, an experimental verification | C111: Wood R.J.; Hamidi H.; Far A.J. | D111: 2024 | E111: Geoenergy Science and Engineering | F111: 10.1016/j.geoen.2024.212783 | G111: R | H111: 13 | I111: 4.33
A112: 8. Pipe Monitoring (Structural/Deposit Sensing) | B112: Fiber Optic Sensor with an Optically Transparent Electrode for Monitoring CaCO3 Scale Formation in Geothermal Water | C112: T. Okazaki; T. Yamamoto; A. Taguchi; A. Ueda; H. Kuramitz | D112: 2017 | E112: IEEE Sensors Letters | F112: 10.1109/LSENS.2017.2739806 | G112: R | H112: 10 | I112: 1
A113: 8. Pipe Monitoring (Structural/Deposit Sensing) | B113: Real-Time Monitoring of CaCO3 Precipitation Using Fiber Optics Scale Sensor Under High Temperature and Pressure Conditions | C113: S. Satake; A. Hosoki; T. Okazaki; A. Ueda; H. Kuramitz; A. Terai | D113: 2024 | E113: 2024 IEEE SENSORS | F113: 10.1109/SENSORS60989.2024.10784725 | G113: R | H113: 1 | I113: 0.33
A114: 8. Pipe Monitoring (Structural/Deposit Sensing) | B114: Novel assessment of in-operations mapped stainless steel elbow pipe internal wall for detection of corrosion and scale deposition | C114: Hamzat A.K.; Memon A.M.; Alhems L.M. | D114: 2022 | E114: International Journal of Corrosion and Scale Inhibition | F114: 10.17675/2305-6894-2022-11-4-5 | G114: R | H114: 1 | I114: 0.2
A115: 8. Pipe Monitoring (Structural/Deposit Sensing) | B115: The Synergistic Effects of Ultrasonic Acoustic Cavitation with ChemicalDissolvers on Calcium Sulfate Scale Dissolution | C115: Canciani C.; Alaseri G.; Alguydi A.; Alissa F. | D115: 2025 | E115: Proceedings of the Annual Offshore Technology Conference | F115: 10.4043/35554-MS | G115: R | H115: 0 | I115: 0
A116: 8. Pipe Monitoring (Structural/Deposit Sensing) | B116: Hetero-Core Fiber Optic SPR Sensor for Silica Scale Formation in Geothermal Water | C116: A. Suka; A. Hosoki; S. Satake; F. Abrishamian; H. Yang; A. Ueda; H. Kuramitz; A. Terai | D116: 2025 | E116: 2025 IEEE SENSORS | F116: 10.1109/SENSORS59705.2025.11330440 | G116: R | H116: 0 | I116: 0
A117: 8. Pipe Monitoring (Structural/Deposit Sensing) | B117: Design and Implementation of a Fan Beam Tomography System for The Performance Evaluation of Geothermal Pipe | C117: Wibisono; F. R. Ningsih; P. Sidauruk; S. K. Wijaya | D117: 2020 | E117: 2020 International Conference on Sustainable Energy Engineering and Application (ICSEEA) | F117: 10.1109/ICSEEA50711.2020.9306184 | G117: M | H117: 0 | I117: 0

Sheet Instructions
A1: Pilot Search Classification & Tracking Workbook
A3: Scale Formation Directed Research — Systematic Review Pilot Stage
A5: How to use this workbook
A6: 1. Go to the 'Search Log' tab — it already records every pilot query run so far (Query 1, Query 5, B1, B2, and the fixes). Add new rows as you run more.
A7: 2. Export each candidate query's results from Scopus/IEEE/WoS/ScienceDirect as CSV, then paste the Authors/Title/Year/Venue/DOI columns into the 'RMI Classification' tab.
A8: 3. For each row, read the title + abstract and set the Tag column to R, M, or I (dropdown provided). Use the Query Source column to mark which candidate query the record came from.
A9: 4. The 'Metrics' tab auto-calculates Direct Relevance % and Coverage % per query — nothing to fill in there, it updates from your tags.
A11: Tag definitions (R / M / I)
A12: R — Relevant: directly studies scale formation/prediction/monitoring/inhibitor optimization in a pipeline, wellbore, reservoir, or production-system context, with a clear method contribution.
A13: M — Maybe: related but unclear — general aqueous/mineral scale chemistry with no stated pipeline/production context, corrosion-focused papers only mentioning scale in passing, or membrane/RO scaling that may be transferable evidence.
A14: I — Irrelevant: clearly off-topic — geology/mineral-genesis papers with no operational relevance, or false-positive term collisions (e.g. "scaling" meaning "scaling up/scalability").
A16: Color legend
A17: Blue text = cells you fill in. Black text = pre-filled data or formulas — don't overwrite formulas. Grey italic = example row, delete or overwrite it before adding real data.

Sheet Search Log
A1: Version | B1: Query Label | C1: Database | D1: Concept-Block Logic | E1: Filters Applied | F1: Date Run | G1: # Results | H1: Decision / Notes
A2: v0.1 | B2: Query 1 (Pilot A — initial) | C2: Scopus | D2: A [incl. bare "scaling"] AND B(species) AND C(context) AND (D OR E) | E2: PUBYEAR 2016–2026, English, Journal+Conference proceeding, Subject area: Energy/ChemEng/Chemistry/Engineering/MaterialsSci/EnvSci | G2: 316 | H2: Baseline high-specificity pilot
A3: v0.2 | B3: Query 5 (Pilot B — initial) | C3: Scopus | D3: A [incl. bare "scaling"] AND C(context) AND (D OR E OR F OR G), species dropped | E3: PUBYEAR 2016–2026, English, Journal+Conference proceeding, Subject area: Energy/ChemEng/Chemistry/Engineering/MaterialsSci/EnvSci | G3: 2557 | H3: ~8x Query 1 — flagged as too broad, decomposed into B1/B2
A4: v0.3 | B4: B1 — isolate species-drop | C4: Scopus | D4: A [incl. bare "scaling"] AND C AND (D OR E), species dropped, OR-group unchanged | E4: PUBYEAR 2016–2026, English, Journal+Conference proceeding, Subject area: Energy/ChemEng/Chemistry/Engineering/MaterialsSci/EnvSci | G4: 1973 | H4: Confirms species-drop is the dominant driver (~6.2x)
A5: v0.4 | B5: B2 — isolate OR-group widening | C5: Scopus | D5: A [incl. bare "scaling"] AND B AND C AND (D OR E OR F OR G), species kept | E5: PUBYEAR 2016–2026, English, Journal+Conference proceeding, Subject area: Energy/ChemEng/Chemistry/Engineering/MaterialsSci/EnvSci | G5: 570 | H5: Modest driver (~1.8x) vs B1's 6.2x — not the main cause
A6: v0.5 | B6: B1 tightened — remove bare "scaling" | C6: Scopus | D6: A [phrases only, no bare "scaling"] AND C AND (D OR E), species dropped | E6: PUBYEAR 2016–2026, English, Journal+Conference proceeding, Subject area: Energy/ChemEng/Chemistry/Engineering/MaterialsSci/EnvSci | G6: 354 | H6: Confirms "scaling" ambiguity caused ~82% of B1's inflation
A7: v0.6 | B7: Query 1 tightened — sanity check | C7: Scopus | D7: A [phrases only, no bare "scaling"] AND B AND C AND (D OR E), species kept | E7: PUBYEAR 2016–2026, English, Journal+Conference proceeding, Subject area: Energy/ChemEng/Chemistry/Engineering/MaterialsSci/EnvSci | G7: 188 | H7: Reveals bare "scaling"+species carries real signal — lost 128 real records
A8: v1.0 | B8: Query verified via Scopus history (303) — CANDIDATE 1 | C8: Scopus | D8: Species mandatory (constant, not a variable) + Block A WITH bare "scaling" + narrow OR-group (D OR E only) + 6 subject areas (no COMP/EART) | E8: PUBYEAR 2016–2026, English, Journal+Conference proceeding, Subject area: Energy/ChemEng/Chemistry/Engineering/MaterialsSci/EnvSci | G8: 303 | H8: RESULT: N=303, R=237 M=41 I=25 -> Direct relevance 78.2%, Coverage 91.7%. CORRECTED NOTE: species was mandatory in BOTH candidates — not the variable being tested.
A9: v1.1 | B9: Query verified via Scopus history (354) — CANDIDATE 2 (FROZEN) | C9: Scopus | D9: Species mandatory (constant) + Block A phrases only (no bare "scaling") + wide OR-group (D OR E OR F OR G combined) + 8 subject areas (+COMP +EART) | E9: PUBYEAR 2016–2026, English, Journal+Conference proceeding, Subject area: Energy/ChemEng/Chemistry/Engineering/MaterialsSci/EnvSci | G9: 354 | H9: RESULT: N=354, R=311 M=34 I=9 -> Direct relevance 87.9%, Coverage 97.5%. RECOMMENDED FROZEN CORE STRING. Higher score vs Candidate 1 is explained by removing the 'scaling' ambiguity + widening the OR-group (F/G folded in) + wider subject net — NOT by species, which was mandatory in both.
B10: B2 (CANDIDATE 3, optional) | C10: Scopus | D10: A [scaling restored] AND B AND C AND (D OR E OR F OR G) | E10: PUBYEAR 2016–2026, English, Journal+Conference proceeding, Subject area: Energy/ChemEng/Chemistry/Engineering/MaterialsSci/EnvSci | G10: 570 | H10: Pending decision whether F/G widening is worth keeping
B11: Query 2 — Objective 1 (sensor fusion) | C11: Scopus | D11: A AND C AND F AND (D OR E) | E11: PUBYEAR 2016–2026, English, Journal+Conference proceeding, Subject area: Energy/ChemEng/Chemistry/Engineering/MaterialsSci/EnvSci | H11: Supplementary probe — run AFTER core string is frozen, not part of Pilot A/B decision
B12: Query 3 — Objective 2 (inhibitor optimization) | C12: Scopus | D12: A AND C AND G AND (D OR E) | E12: PUBYEAR 2016–2026, English, Journal+Conference proceeding, Subject area: Energy/ChemEng/Chemistry/Engineering/MaterialsSci/EnvSci | H12: Supplementary probe — run AFTER core string is frozen
B13: Query 4 — Objective 3 (digital twin/decision support) | C13: Scopus | D13: A AND C AND (F OR H) AND (SCADA/digital twin/decision support) | E13: PUBYEAR 2016–2026, English, Journal+Conference proceeding, Subject area: Energy/ChemEng/Chemistry/Engineering/MaterialsSci/EnvSci | H13: Supplementary probe — low count expected = gap evidence, not a failed search
A15: DECISION | B15: Frozen core search string = 354-query (verified via Scopus history): species mandatory + Block A phrases only (no bare 'scaling') + full (D OR E OR F OR G) OR-group + 8 subject areas incl. COMP/EART. Objective-specific probes (Queries 2-4) are now redundant since F/G are already folded into this frozen string.
A16: v2.0 | B16: IEEE Xplore — Block D (methodology/kinetics) | C16: IEEE Xplore | D16: A AND B(species) AND C(context) AND D, tag-per-term syntax (grouped tag syntax returned 0 results — IEEE parser bug) | E16: PUBYEAR 2016-2026, English, Full Text & Metadata field, run as 4 separate sub-searches (Row4 swapped per block) due to institutional network rejecting the single combined Command Search URL | G16: 18 | H16: RESULT: R=5 M=3 I=10 -> Direct relevance 27.8%, Coverage 44.4%
A17: v2.1 | B17: IEEE Xplore — Block E (AI/ML) | C17: IEEE Xplore | D17: A AND B AND C AND E | E17: PUBYEAR 2016-2026, English, Full Text & Metadata field, run as 4 separate sub-searches (Row4 swapped per block) due to institutional network rejecting the single combined Command Search URL | G17: 5 | H17: RESULT: R=2 M=1 I=2 -> Direct relevance 40.0%, Coverage 60.0%
A18: v2.2 | B18: IEEE Xplore — Block F (sensing/monitoring) | C18: IEEE Xplore | D18: A AND B AND C AND F | E18: PUBYEAR 2016-2026, English, Full Text & Metadata field, run as 4 separate sub-searches (Row4 swapped per block) due to institutional network rejecting the single combined Command Search URL | G18: 13 | H18: RESULT: R=5 M=2 I=6 -> Direct relevance 38.5%, Coverage 53.8%
A19: v2.3 | B19: IEEE Xplore — Block G (inhibitor/dosage) | C19: IEEE Xplore | D19: A AND B AND C AND G | E19: PUBYEAR 2016-2026, English, Full Text & Metadata field, run as 4 separate sub-searches (Row4 swapped per block) due to institutional network rejecting the single combined Command Search URL | G19: 11 | H19: RESULT: R=1 M=3 I=7 -> Direct relevance 9.1%, Coverage 36.4%. Weakest block — IEEE has little inhibitor-chemistry literature
A20: v2.SUM | B20: IEEE Xplore — combined unique set (27 after dedup across D/E/F/G) | C20: IEEE Xplore | H20: RESULT: R=8 M=7 I=12 -> Direct relevance 29.6%, Coverage 55.6%. Much noisier than Scopus (book-chapter/TOC indexing artifacts + off-domain hits) — expected, IEEE is not a petroleum-chemistry-focused database.
A21: v3.0 | B21: Web of Science Core Collection — frozen query | C21: Web of Science | D21: TS=(A AND B AND C AND (D OR E OR F OR G)) AND PY=(2016-2026), Full Record export | E21: PY=2016-2026, single unified TS= query (same frozen logic as Scopus/IEEE) | G21: 192 | H21: RESULT: R=158 M=24 I=10 -> Direct relevance 82.3%, Coverage 94.8%. Strong overlap with Scopus (123/192 titles already classified there) — second-strongest database after Scopus, far ahead of IEEE.
A22: v4.0 | B22: ScienceDirect — Query 1 (species+context+prediction/inhibitor) | C22: ScienceDirect | D22: "scale formation" AND (CaCO3 OR BaSO4 OR SrSO4) AND (pipeline OR oilfield OR reservoir) AND (prediction OR inhibitor) | E22: 8-Boolean-connector cap forced heavy query simplification; PY=2016-2026 | G22: 2 | H22: RESULT: R=2 M=0 I=0 -> Direct relevance 100%. Both directly relevant oilfield scale-inhibitor papers.
A23: v4.1 | B23: ScienceDirect — Query 2 (species+context+AI/monitoring) | C23: ScienceDirect | D23: "scale formation" AND (CaCO3 OR BaSO4 OR SrSO4) AND (pipeline OR oilfield OR reservoir) AND ("machine learning" OR monitoring) | E23: 8-Boolean-connector cap forced heavy query simplification; PY=2016-2026 | G23: 1 | H23: RESULT: duplicate of a Query 1 record - no unique contribution. Combined unique ScienceDirect corpus = 2 records.
A24: v5.0 | B24: Saudi Digital Library (SDL) -- supplementary search | C24: Saudi Digital Library (SDL) | D24: ("scale formation" OR "scale deposition" OR "mineral scaling") AND (CaCO3 OR BaSO4 OR SrSO4 OR carbonate scale OR sulfate scale) AND (pipeline OR wellbore OR oilfield OR "flow assurance") AND (inhibitor OR kinetics OR sensing OR prediction OR "machine learning") | E24: Source Types: Academic Journals; Language: English; Published Date 2016-10-01 to 2026-10-01; federated search across OpenAIRE, DOAJ, MEDLINE, RePEc (via EBSCO Discovery API) | G24: 59 | H24: RESULT: 59 unique records returned (75 raw, 59 deduped by SDL's own engine). Cross-matched by DOI/title against the existing 439-record master corpus: 38 were already captured via Scopus/WoS (expected -- SDL is a federated discovery layer re-indexing the same publishers), 21 genuinely new. Of the 21 new: R=18 M=1 I=2 -> Direct relevance 85.7%, Coverage 90.5%. Strong supplementary yield, on par with WoS.

Sheet RMI Classification
A1: Record ID | B1: Authors | C1: Title | D1: Year | E1: Venue / Source | F1: DOI | G1: Query Source | H1: Tag (R/M/I) | I1: Reason / Note
A2: EX-001 | B2: Tomson, M.B. et al. | C2: EXAMPLE ROW — delete before adding real data: Coupled thermodynamic-kinetic modeling of CaCO3 scale deposition in production tubing | D2: 2019 | E2: Journal of Petroleum Science and Engineering | F2: 10.1016/j.example | G2: v1.0 Core query (303) | H2: R | I2: Direct pipeline scale-prediction study with quantitative kinetic model
A3: U001 | B3: Wang X.; Chen X.; Ma C.; Lu S.; Zhang L.; Chen Y.; Hushvaktov H.; Zhang X. | C3: A DNN surrogate framework with mode-aware scoring for blast-resistant design of CFRP-steel fiber metal laminates | D3: 2026 | E3: Journal of Materials Research and Technology | F3: 10.1016/j.jmrt.2026.08.159 | G3: v1.0 Core query (303) | H3: I | I3: Blast-resistant CFRP-steel laminate structural design; no scale-formation relevance
A4: U002 | B4: Maciel R.S.; Carneiro J.N.E.; Souza A.F.F.; Monteiro D.; Gunnerud V. | C4: A method for inorganic scaling simulation: multiphase flow and multi-ionic brine with a mass transfer approach | D4: 2026 | E4: Journal of the Brazilian Society of Mechanical Sciences and Engineering | F4: 10.1007/s40430-025-06290-6 | G4: v1.0 Core query (303) | H4: R | I4: Inorganic scaling simulation, multiphase flow, pre-salt reservoir flow assurance
A5: U003 | B5: Moussa B.; Med Ali A.; Abdeljaber T.; Mohamed Abdelbasset M. | C5: Artificial-intelligence modeling of carbonate scaling tendency in Hassi Messaoud oilfield groundwater: linear versus nonlinear approaches | D5: 2026 | E5: Journal of African Earth Sciences | F5: 10.1016/j.jafrearsci.2026.106243 | G5: v1.1 B1 tightened (354) | H5: R | I5: AI modeling of carbonate scaling tendency, oilfield groundwater, explicit
A6: U004 | B6: Ma C.; Tong Y. | C6: Co-deposition of calcium carbonate and barium sulfate on the surface of iron-based pipe scaling mechanism and descaling agent system research | D6: 2026 | E6: Surfaces and Interfaces | F6: 10.1016/j.surfin.2026.109312 | G6: v1.0 Core query (303) | H6: R | I6: CaCO3+BaSO4 co-deposition on iron pipe, descaling agent, oil&gas production
A7: U005 | B7: Ali H.A.; El-Makaty F.M.; Liu M.; Li X.; Mady M.F. | C7: Comparative performance of silica vs mesoporous silica nanoparticles coated with DTPMP for gypsum and calcite management | D7: 2026 | E7: Journal of Water Process Engineering | F7: 10.1016/j.jwpe.2026.109939 | G7: v1.1 B1 tightened (354) | H7: R | I7: Nanoparticle inhibitors for gypsum/calcite, explicit oil and gas production
A8: U006 | B8: Goswami S.; Rai A.K. | C8: Coupled hydrogeological and geochemical processes and structural controls on geothermal systems in Odisha, India | D8: 2026 | E8: Environmental Earth Sciences | F8: 10.1007/s12665-026-13009-w | G8: v1.0 Core query (303) | H8: I | I8: Geothermal hydrogeochemistry/structural study, no scale-formation focus
A9: U007 | B9: Lagarrigue E.; Rachid Haro R.G.; Arali V.; Araque G.; Misbah M.; Ryan A.; Mendez A.; Illa X. | C9: Development and Qualification of an Ultra-High-Salinity Fracturing Fluid with Integrated Friction Reduction and Scale Control for Water-Constrained Fields | D9: 2026 | E9: Society of Petroleum Engineers - SPE Hydraulic Fracturing Technology Conference and Exhibition, HFTC 2026 | F9: 10.2118/230627-MS | G9: v1.0 Core query (303) | H9: R | I9: Fracturing fluid with integrated scale inhibitor testing, water-constrained oilfields
A10: U008 | B10: Ganie S.A.; Khaled M.; Mady M.F. | C10: Dicarboxylated Alginic Acid as a Dual-Functional Corrosion and Scale Inhibitor for Oil and Gas Industry | D10: 2026 | E10: Energy and Fuels | F10: 10.1021/acs.energyfuels.5c06808 | G10: v1.0 Core query (303) | H10: R | I10: Dual corrosion+scale inhibitor, explicit oil and gas industry
A11: U008 | B11: Ganie S.A.; Khaled M.; Mady M.F. | C11: Dicarboxylated Alginic Acid as a Dual-Functional Corrosion and Scale Inhibitor for Oil and Gas Industry | D11: 2026 | E11: Energy and Fuels | F11: 10.1021/acs.energyfuels.5c06808 | G11: v1.1 B1 tightened (354) | H11: R | I11: Dual corrosion+scale inhibitor, explicit oil and gas industry
A12: U009 | B12: Sui X.; Wang Z.; Sun B.; Guo Y. | C12: Dynamic Calcium Carbonate Scaling in Porous Media under Gas/Liquid Two-Phase Flow Conditions | D12: 2026 | E12: SPE Journal | F12: 10.2118/231846-PA | G12: v1.0 Core query (303) | H12: R | I12: Dynamic CaCO3 scaling in porous media, gas well reservoir, explicit
A13: U009 | B13: Sui X.; Wang Z.; Sun B.; Guo Y. | C13: Dynamic Calcium Carbonate Scaling in Porous Media under Gas/Liquid Two-Phase Flow Conditions | D13: 2026 | E13: SPE Journal | F13: 10.2118/231846-PA | G13: v1.1 B1 tightened (354) | H13: R | I13: Dynamic CaCO3 scaling in porous media, gas well reservoir, explicit
... A98: U072 | B98: Al-Salal M.; Al-Mass S.; Al-Abbasi K.; Kakade S.; Boareki N.; Al-Rashedi H.; Dashti B.; Karadi N.; Munck D.; Madsen T.; Lydersen M. | C98: Pioneering Advanced Ceramic Water Filtration Compact Skids for Efficient Water Injection in Tight Reservoirs: A Successful Pilot in Abduliyah Field | D98: 2025 | E98: Society of Petroleum Engineers - ADIPEC 2025 | F98: 10.2118/230135-MS | G98: v1.1 B1 tightened (354) | H98: M | I98: Ceramic water filtration skids for water injection - filtration tech, not scale focus
A99: U073 | B99: Johnson A.; Mroczek E.; Akerley J.; Webbison S. | C99: Predicting Calcite Scale in the Geothermal Industry: Recent Insights and Application to Single and Two-Phase Fluid Modeling at Two Ormat Facilities | D99: 2025 | E99: Transactions - Geothermal Resources Council | G99: v1.0 Core query (303) | H99: M | I99: Calcite scale prediction, geothermal industry (Ormat) - adjacent industry
A100: U074 | B100: Hu Z.; Luo X. | C100: Prediction of Calcite Induction Time Using Machine Learning | D100: 2025 | E100: 2025 7th International Conference on Frontier Technologies of Information and Computer, ICFTIC 2025 | F100: 10.1109/ICFTIC68075.2025.11324549 | G100: v1.0 Core query (303) | H100: R | I100: ML prediction of calcite induction time, inhibitor dosing optimization
A101: U075 | B101: Alayande S.B.; Alawode A.J. | C101: Prediction of Permeability Impairment Due to Scale Deposition in Waterflooding Using Machine Learning Algorithm | D101: 2025 | E101: Society of Petroleum Engineers - SPE Nigeria Annual International Conference and Exhibition, NAIC 2025 | F101: 10.2118/228768-MS | G101: v1.0 Core query (303) | H101: R | I101: ML permeability impairment from scale deposition, waterflooding, oil and gas
A102: U075 | B102: Alayande S.B.; Alawode A.J. | C102: Prediction of Permeability Impairment Due to Scale Deposition in Waterflooding Using Machine Learning Algorithm | D102: 2025 | E102: Society of Petroleum Engineers - SPE Nigeria Annual International Conference and Exhibition, NAIC 2025 | F102: 10.2118/228768-MS | G102: v1.1 B1 tightened (354) | H102: R | I102: ML permeability impairment from scale deposition, waterflooding, oil and gas
A103: U076 | B103: Belkacem O.; Rezrazi A.; Aizi K.; Abdelouahed L.; Laidi M.; Touil A.; Cherifi L.; Hanini S. | C103: Prediction of barite scale formation and inhibition in hydrocarbon reservoirs using AI modeling: Focus on different optimization algorithms | D103: 2025 | E103: Results in Engineering | F103: 10.1016/j.rineng.2025.105222 | G103: v1.0 Core query (303) | H103: R | I103: AI barite scale formation/inhibition, hydrocarbon reservoirs waterflooding
A104: U076 | B104: Belkacem O.; Rezrazi A.; Aizi K.; Abdelouahed L.; Laidi M.; Touil A.; Cherifi L.; Hanini S. | C104: Prediction of barite scale formation and inhibition in hydrocarbon reservoirs using AI modeling: Focus on different optimization algorithms | D104: 2025 | E104: Results in Engineering | F104: 10.1016/j.rineng.2025.105222 | G104: v1.1 B1 tightened (354) | H104: R | I104: AI barite scale formation/inhibition, hydrocarbon reservoirs waterflooding
A105: U077 | B105: Candra A.D.; Agin L.F.P.; Wicaksono W.P.A. | C105: Quantitative Assessment of Calcite Scaling of a Vapour-Dominated Well | D105: 2025 | E105: Scientific Contributions Oil and Gas | F105: 10.29017/scog.v48i4.1861 | G105: v1.0 Core query (303) | H105: M | I105: Calcite scaling, vapour-dominated geothermal well - adjacent industry
A106: U078 | B106: Ness G.; Spica C.; Petteruti E.; Cavaioni P. | C106: Root Cause Analysis of Calcite Scale Deposition in Gas Wells Using Rigorous Scale Predictions and Kinetics of Scale Formation | D106: 2025 | E106: Proceedings - SPE International Symposium on Oilfield Chemistry | F106: 10.2118/224269-MS | G106: v1.0 Core query (303) | H106: R | I106: Calcite scale deposition root-cause+kinetics, Algerian gas field
A107: U078 | B107: Ness G.; Spica C.; Petteruti E.; Cavaioni P. | C107: Root Cause Analysis of Calcite Scale Deposition in Gas Wells Using Rigorous Scale Predictions and Kinetics of Scale Formation | D107: 2025 | E107: Proceedings - SPE International Symposium on Oilfield Chemistry | F107: 10.2118/224269-MS | G107: v1.1 B1 tightened (354) | H107: R | I107: Calcite scale deposition root-cause+kinetics, Algerian gas field
A108: U079 | B108: Zhang B.; Zhang X.; Zhang L.; Ali S.I.; Tariq S.M. | C108: Scale precipitation modeling in the presence of scale inhibitors using MSE–SRK model | D108: 2025 | E108: Chemical Papers | F108: 10.1007/s11696-025-04264-5 | G108: v1.0 Core query (303) | H108: R | I108: Scale precipitation modeling with inhibitors, MSE-SRK, oilfield flow-assurance software
A109: U079 | B109: Zhang B.; Zhang X.; Zhang L.; Ali S.I.; Tariq S.M. | C109: Scale precipitation modeling in the presence of scale inhibitors using MSE–SRK model | D109: 2025 | E109: Chemical Papers | F109: 10.1007/s11696-025-04264-5 | G109: v1.1 B1 tightened (354) | H109: R | I109: Scale precipitation modeling with inhibitors, MSE-SRK, oilfield flow-assurance software
A110: U080 | B110: Ferreira F.A.V.; Dantas E.D.; Penha V.C.; Andrade D.C.; Pereira L.; Chiavone-Filho O. | C110: Solubility of Calcium Carbonate in Aqueous Monoethylene Glycol Mixtures under a Carbon Dioxide Atmosphere Using an Analytical Method | D110: 2025 | E110: Journal of Chemical and Engineering Data | F110: 10.1021/acs.jced.4c00670 | G110: v1.0 Core query (303) | H110: R | I110: CaCO3 solubility in MEG/CO2, explicit pipeline scaling in gas production
A111: U081 | B111: Canciani C.; Alaseri G.; Alguydi A.; Alissa F. | C111: The Synergistic Effects of Ultrasonic Acoustic Cavitation with ChemicalDissolvers on Calcium Sulfate Scale Dissolution | D111: 2025 | E111: Proceedings of the Annual Offshore Technology Conference | F111: 10.4043/35554-MS | G111: v1.1 B1 tightened (354) | H111: R | I111: Ultrasonic+chemical dissolvers CaSO4 scale dissolution, oilfields, explicit
... A122: U091 | B122: Albaiz A.; Almubarak T.; Alissa F.; Owais A.; Aljeaban N. | C122: Calcium Sulfate Scale Inhibitor: Does the Carbon Backbone Length Matter? | D122: 2024 | E122: International Petroleum Technology Conference, IPTC 2024 | F122: 10.2523/IPTC-23506-EA | G122: v1.1 B1 tightened (354) | H122: R | I122: CaSO4 scale inhibitor structure-activity, oil and gas industry explicit
A123: U092 | B123: Lu H.; Wei W.; Wang W.; Yan C.; Young R.; Nix D. | C123: Case Histories of Permian Area Scale Treatment Challenges and Chemical Program Optimization Strategies | D123: 2024 | E123: AMPP Annual Conference and Expo 2024 | G123: v1.1 B1 tightened (354) | H123: R | I123: Permian scale treatment case histories, chemical program optimization
A124: U093 | B124: Al Hinai M.I.; Al-Yaaribi A.; Al Qassabi H.A.; Al Aamri G.; Al-Hinai N.; Al Saadi F.; Abdullah I.B.; Al Zadjali A. | C124: Case Study Southern Oil Field Oman: Novel Approach in Optimizing Dispersed Acid System for Matrix Stimulation in Water Injectors to Improve Injectivity | D124: 2024 | E124: Society of Petroleum Engineers - SPE Symposium and Exhibition - Production Enhancement and Cost Optimisation, SM02 2024 | F124: 10.2118/220635-MS | G124: v1.1 B1 tightened (354) | H124: R | I124: Dispersed acid system water injectors Oman, scale/damage injectivity
A125: U094 | B125: Amin S.; Kazama S.; Sawangjang B.; Takizawa S. | C125: Causes and Effects of Scale Deposition in Water Supply Pipelines in Surakarta City, Indonesia | D125: 2024 | E125: Water (Switzerland) | F125: 10.3390/w16162275 | G125: v1.0 Core query (303) | H125: M | I125: Water supply pipelines Surakarta Indonesia scale deposition - municipal, not oilfield
A126: U094 | B126: Amin S.; Kazama S.; Sawangjang B.; Takizawa S. | C126: Causes and Effects of Scale Deposition in Water Supply Pipelines in Surakarta City, Indonesia | D126: 2024 | E126: Water (Switzerland) | F126: 10.3390/w16162275 | G126: v1.1 B1 tightened (354) | H126: M | I126: Water supply pipelines Surakarta Indonesia scale deposition - municipal, not oilfield
A127: U095 | B127: Wang L.-C.; Che Y.; Zhu Y.-R.; Guo S.-L.; Ma W.; Zhao Q.-L.; Li G.; Wang L.-B. | C127: Comparative study of a low phosphorous co-polymer inhibitor with commercial scale inhibitors used in cooling water systems | D127: 2024 | E127: Journal of Applied Polymer Science | F127: 10.1002/app.55145 | G127: v1.1 B1 tightened (354) | H127: M | I127: Low-phosphorus copolymer inhibitor cooling water systems - industrial, not oilfield
A128: U096 | B128: Hosseini E.; Mohammad Nazar D.; Hosseini N.; Sarmadivaleh M. | C128: Developing a phenomenological model to simulate single and mixed scale formation during flow in porous media: Coupling a salt precipitation model with an ion transport equation under dynamic conditions | D128: 2024 | E128: Petroleum Research | F128: 10.1016/j.ptlrs.2023.09.003 | G128: v1.0 Core query (303) | H128: R | I128: Phenomenological salt precipitation model, porous media waterflooding, petroleum
A129: U096 | B129: Hosseini E.; Mohammad Nazar D.; Hosseini N.; Sarmadivaleh M. | C129: Developing a phenomenological model to simulate single and mixed scale formation during flow in porous media: Coupling a salt precipitation model with an ion transport equation under dynamic conditions | D129: 2024 | E129: Petroleum Research | F129: 10.1016/j.ptlrs.2023.09.003 | G129: v1.1 B1 tightened (354) | H129: R | I129: Phenomenological salt precipitation model, porous media waterflooding, petroleum
A130: U097 | B130: Paudyal S.; Fan C. | C130: Development of Inorganic Scale Inhibitors for Ultrahigh-Temperatures Geothermal and HPHT Applications | D130: 2024 | E130: AMPP Annual Conference and Expo 2024 | G130: v1.1 B1 tightened (354) | H130: R | I130: Inorganic SI ultrahigh-temp geothermal AND HPHT oil/gas applications, explicit
A131: U098 | B131: Meybodi M.K.; Vazquez O.; Sorbie K.S.; Mackay E.J.; Jarrahian K. | C131: Equilibrium Modelling of Interactions in DETPMP-Carbonate System | D131: 2024 | E131: Society of Petroleum Engineers - SPE Oilfield Scale Symposium, OSS 2024 | F131: 10.2118/218704-MS | G131: v1.1 B1 tightened (354) | H131: R | I131: DETPMP-carbonate equilibrium modeling, SI squeeze treatments oil and gas
A132: U099 | B132: Oliveira J.; Ortiz R.W.P.; Passos N.S.; Venancio F.; Gonçalves V.O.O.; Cajaiba J.; Ribeiro-Santos R.; Perrone D.; Kartnaller V. | C132: Evaluating starchy food effluents as potential green inhibitors of calcium carbonate scale in oil and gas production | D132: 2024 | E132: Brazilian Journal of Chemical Engineering | F132: 10.1007/s43153-023-00404-0 | G132: v1.0 Core query (303) | H132: R | I132: Starchy food effluent green CaCO3 scale inhibitors, oil and gas production
A133: U099 | B133: Oliveira J.; Ortiz R.W.P.; Passos N.S.; Venancio F.; Gonçalves V.O.O.; Cajaiba J.; Ribeiro-Santos R.; Perrone D.; Kartnaller V. | C133: Evaluating starchy food effluents as potential green inhibitors of calcium carbonate scale in oil and gas production | D133: 2024 | E133: Brazilian Journal of Chemical Engineering | F133: 10.1007/s43153-023-00404-0 | G133: v1.1 B1 tightened (354) | H133: R | I133: Starchy food effluent green CaCO3 scale inhibitors, oil and gas production
A134: U100 | B134: Fan C.; Aloke O.; Nelson A.C.; Temple E. | C134: Evaluation of Scale Dissolver Products for Near-Wellbore Applications | D134: 2024 | E134: Society of Petroleum Engineers - SPE Oilfield Scale Symposium, OSS 2024 | F134: 10.2118/218733-MS | G134: v1.1 B1 tightened (354) | H134: R | I134: Scale dissolver products near-wellbore, flowlines/tubing/wellbore explicit
A135: U101 | B135: Hussein M.F.; Mubarak M.F.; Al-Sirhani A.M.; Hosny R. | C135: Examining the factors that impact the formation of barite scale in water injection operations: experimental study and quantification of scale formation | D135: 2024 | E135: Discover Applied Sciences | F135: 10.1007/s42452-024-06176-7 | G135: v1.1 B1 tightened (354) | H135: R | I135: Factors impacting barite scale, water injection operations, oilfield explicit
A136: U102 | B136: Kamaratou M.; Spinthaki A.; Disci D.; Demadis K.D. | C136: Ferric silicate precipitates relevant to geothermal systems: Delineation of their complex formation | D136: 2024 | E136: Geothermics | F136: 10.1016/j.geothermics.2024.103118 | G136: v1.0 Core query (303) | H136: M | I136: Ferric silicate precipitates in geothermal systems - adjacent industry
A137: U103 | B137: Lu A.Y.-T.; Yue Z. | C137: Field Case Study: Impact of Corrosion Inhibitor on Scale Control | D137: 2024 | E137: AMPP Annual Conference and Expo 2024 | G137: v1.0 Core query (303) | H137: R | I137: Corrosion inhibitor impact on scale control, Permian Basin field case
A138: U103 | B138: Lu A.Y.-T.; Yue Z. | C138: Field Case Study: Impact of Corrosion Inhibitor on Scale Control | D138: 2024 | E138: AMPP Annual Conference and Expo 2024 | G138: v1.1 B1 tightened (354) | H138: R | I138: Corrosion inhibitor impact on scale control, Permian Basin field case
A139: U104 | B139: Co N.E.C.; Hugaas B.-A.; Krishnamurthy R.M.; Fredriksen R.M.; George K.; Hjelle S.O. | C139: H2S, CO2 and High Chloride Downhole Environment Modelling and Fitness for Purpose Testing of UNS S39274, UNS N08535 and UNS N06255 Corrosion Resistant Alloys | D139: 2024 | E139: AMPP Annual Conference and Expo 2024 | G139: v1.0 Core query (303) | H139: I | I139: Corrosion-resistant alloy testing H2S/CO2/chloride - metallurgy, not scale formation
A140: U105 | B140: Shen Y.-Y.; Deng G.; Wang X.; Ye Y.; Reiss A.; Yao X.; Pimentel D.; Leschied C.; Kan A.T.; Tomson M.B. | C140: Impact of High Calcium Concentrations on Barite Scale Prediction Under High Temperature and High Pressure Conditions | D140: 2024 | E140: Society of Petroleum Engineers - SPE Oilfield Scale Symposium, OSS 2024 | F140: 10.2118/218707-MS | G140: v1.0 Core query (303) | H140: R | I140: Barite scale prediction HTHP high calcium, oil and gas industry explicit
A141: U105 | B141: Shen Y.-Y.; Deng G.; Wang X.; Ye Y.; Reiss A.; Yao X.; Pimentel D.; Leschied C.; Kan A.T.; Tomson M.B. | C141: Impact of High Calcium Concentrations on Barite Scale Prediction Under High Temperature and High Pressure Conditions | D141: 2024 | E141: Society of Petroleum Engineers - SPE Oilfield Scale Symposium, OSS 2024 | F141: 10.2118/218707-MS | G141: v1.1 B1 tightened (354) | H141: R | I141: Barite scale prediction HTHP high calcium, oil and gas industry explicit
A142: U106 | B142: Baraka-Lokmane S.; de Sousa A.M. | C142: Impact of Methanol on the Scale Deposition - a Case Study from West Africa | D142: 2024 | E142: Society of Petroleum Engineers - ADIPEC 2024 | F142: 10.2118/222746-MS | G142: v1.0 Core query (303) | H142: R | I142: Methanol impact on scale deposition, West Africa field case, explicit
A143: U106 | B143: Baraka-Lokmane S.; de Sousa A.M. | C143: Impact of Methanol on the Scale Deposition - a Case Study from West Africa | D143: 2024 | E143: Society of Petroleum Engineers - ADIPEC 2024 | F143: 10.2118/222746-MS | G143: v1.1 B1 tightened (354) | H143: R | I143: Methanol impact on scale deposition, West Africa field case, explicit
A144: U107 | B144: Chen H.; Zhu S.S. | C144: Improving Saline Aquifer Caprock Integrity in CO2 Geosequestration Using Waste Plastics | D144: 2024 | E144: SPE Annual Technical Conference Proceedings | F144: 10.2118/220803-MS | G144: v1.0 Core query (303) | H144: I | I144: CO2 geosequestration caprock integrity via waste plastics - seal integrity, not scale mgmt
A145: U107 | B145: Chen H.; Zhu S.S. | C145: Improving Saline Aquifer Caprock Integrity in CO2 Geosequestration Using Waste Plastics | D145: 2024 | E145: SPE Annual Technical Conference Proceedings | F145: 10.2118/220803-MS | G145: v1.1 B1 tightened (354) | H145: I | I145: CO2 geosequestration caprock integrity via waste plastics - seal integrity, not scale mgmt
A146: U108 | B146: Chen H.; Sherry Zhu S. | C146: Improving Saline Aquifer Caprock Integrity in CO2 Geosequestration Using Waste Plastics | D146: 2024 | E146: Proceedings - SPE Annual Technical Conference and Exhibition | F146: 10.2118/220803-MS | G146: v1.0 Core query (303) | H146: I | I146: Duplicate of U107 - same tag
A147: U108 | B147: Chen H.; Sherry Zhu S. | C147: Improving Saline Aquifer Caprock Integrity in CO2 Geosequestration Using Waste Plastics | D147: 2024 | E147: Proceedings - SPE Annual Technical Conference and Exhibition | F147: 10.2118/220803-MS | G147: v1.1 B1 tightened (354) | H147: I | I147: Duplicate of U107 - same tag
A148: U109 | B148: Wang M.; Zuo X.; Jacovone R.M.S.; O'Hara R.; Mondal A.N.; Asatekin A.; Rodrigues D.F. | C148: Influence of zwitterionic amphiphilic copolymers on heterogeneous gypsum formation: A promising approach for scaling resistance | D148: 2024 | E148: Water Research | F148: 10.1016/j.watres.2024.122439 | G148: v1.0 Core query (303) | H148: M | I148: Zwitterionic copolymers gypsum formation - multi-industry fundamental study
A149: U110 | B149: Wang Q.; Chen T. | C149: Inhibition of calcium carbonate scale under severe conditions | D149: 2024 | E149: Petroleum Science and Technology | F149: 10.1080/10916466.2022.2158199 | G149: v1.0 Core query (303) | H149: R | I149: CaCO3 scale inhibition severe conditions, dynamic scale loop tests (oilfield method)
A150: U110 | B150: Wang Q.; Chen T. | C150: Inhibition of calcium carbonate scale under severe conditions | D150: 2024 | E150: Petroleum Science and Technology | F150: 10.1080/10916466.2022.2158199 | G150: v1.1 B1 tightened (354) | H150: R | I150: CaCO3 scale inhibition severe conditions, dynamic scale loop tests (oilfield method)
A151: U111 | B151: Murtaza M.; Budiman O.; Kamal M.S.; Alajmi S.N.; Al-Jawad M.; Mahmoud M. | C151: Ionic Liquid-Based Formulation for Inhibiting Calcium Sulfate Scale in High-Pressure High-Temperature Wells | D151: 2024 | E151: Society of Petroleum Engineers - ADIPEC 2024 | F151: 10.2118/222368-MS | G151: v1.1 B1 tightened (354) | H151: R | I151: Ionic liquid CaSO4 scale inhibition HPHT wells, oil and gas operations explicit
... A177: U129 | B177: Jarrahian K.; Mackay E.; Singleton M.; Mohammadi S.; Heath S.; Pessu F. | C177: Scale Control in Geothermal Wells – What are the Options for Effective and Economic Scale Management? | D177: 2024 | E177: Society of Petroleum Engineers - SPE Oilfield Scale Symposium, OSS 2024 | F177: 10.2118/218737-MS | G177: v1.1 B1 tightened (354) | H177: M | I177: Scale control options for geothermal wells - geothermal industry
A178: U130 | B178: Das G.; Springer R.D.; Kosinski J.; Anderko A. | C178: Scaling Risk Assessment and Remediation in Geothermal Operations Using a Novel Theoretical Approach | D178: 2024 | E178: AMPP Annual Conference and Expo 2024 | G178: v1.0 Core query (303) | H178: M | I178: Scaling risk assessment geothermal operations - geothermal industry
A179: U131 | B179: Benkhaled M.; Tort F.; Baraka-Lokmane S.; Fretard D.; Lesage N. | C179: Strategic Scale Mitigation for Oil Wells with a Low Basic Sediment and Water | D179: 2024 | E179: Society of Petroleum Engineers - SPE Oilfield Scale Symposium, OSS 2024 | F179: 10.2118/218702-MS | G179: v1.0 Core query (303) | H179: R | I179: Strategic scale mitigation oil wells low BSW, onshore field, explicit
A180: U131 | B180: Benkhaled M.; Tort F.; Baraka-Lokmane S.; Fretard D.; Lesage N. | C180: Strategic Scale Mitigation for Oil Wells with a Low Basic Sediment and Water | D180: 2024 | E180: Society of Petroleum Engineers - SPE Oilfield Scale Symposium, OSS 2024 | F180: 10.2118/218702-MS | G180: v1.1 B1 tightened (354) | H180: R | I180: Strategic scale mitigation oil wells low BSW, onshore field, explicit
A181: U132 | B181: Lobo J.S.; Serpa F.S.; Filho E.B.M.; Castro B.B.; Borges G.R.; Dariva C.; Franceschi E. | C181: Study of the kinetic behavior of chemical inhibitors in calcium carbonate scale formation | D181: 2024 | E181: Brazilian Journal of Chemical Engineering | F181: 10.1007/s43153-023-00328-9 | G181: v1.0 Core query (303) | H181: R | I181: Kinetic behavior of chemical inhibitors in CaCO3 scale formation, oil and gas
A182: U132 | B182: Lobo J.S.; Serpa F.S.; Filho E.B.M.; Castro B.B.; Borges G.R.; Dariva C.; Franceschi E. | C182: Study of the kinetic behavior of chemical inhibitors in calcium carbonate scale formation | D182: 2024 | E182: Brazilian Journal of Chemical Engineering | F182: 10.1007/s43153-023-00328-9 | G182: v1.1 B1 tightened (354) | H182: R | I182: Kinetic behavior of chemical inhibitors in CaCO3 scale formation, oil and gas
A183: U133 | B183: Zhao L.; Zhang Y.; He Y.; Yang Z.; Liang X.; Wang X.; Mao Q. | C183: Study on the Mechanism of Wellbore Blockage and Scaling Trend Prediction of Keshen Block | D183: 2024 | E183: Processes | F183: 10.3390/pr12040782 | G183: v1.1 B1 tightened (354) | H183: R | I183: Wellbore blockage mechanism/scaling trend prediction, Tarim Basin gas field
A184: U134 | B184: Garayev M.; Adoga C.; Trim S.; Brand P. | C184: Subsea Pelican Oil Field Scale Management and Production Enhancement | D184: 2024 | E184: Society of Petroleum Engineers - SPE Oilfield Scale Symposium, OSS 2024 | F184: 10.2118/218720-MS | G184: v1.1 B1 tightened (354) | H184: R | I184: Subsea oil field scale management production enhancement, Pelican field, barite
A185: U135 | B185: Ganguly S.; Kelland M.A.; Ellis R.J.; Andresen M.; Subramanian S.; Theodossiou A. | C185: Sustainable Calcite Scale Inhibitors via Oxidation of Lignosulfonates | D185: 2024 | E185: ACS Omega | F185: 10.1021/acsomega.4c02716 | G185: v1.0 Core query (303) | H185: R | I185: Sustainable calcite SI via lignosulfonates, upstream oil and gas explicit
A186: U135 | B186: Ganguly S.; Kelland M.A.; Ellis R.J.; Andresen M.; Subramanian S.; Theodossiou A. | C186: Sustainable Calcite Scale Inhibitors via Oxidation of Lignosulfonates | D186: 2024 | E186: ACS Omega | F186: 10.1021/acsomega.4c02716 | G186: v1.1 B1 tightened (354) | H186: R | I186: Sustainable calcite SI via lignosulfonates, upstream oil and gas explicit
A187: U136 | B187: Johnston C.J.; Jordan M.M.; Vikshaland K.; Johnston M. | C187: Synergistic Scale Inhibitor Blends for Severe Carbonate Scaling Systems | D187: 2024 | E187: International Petroleum Technology Conference, IPTC 2024 | F187: 10.2523/IPTC-24584-EA | G187: v1.1 B1 tightened (354) | H187: R | I187: Synergistic SI blends severe carbonate scaling, oilfield chemical industry
A188: U137 | B188: El-Sawaf A.K.; Mubarak M.F.; Selim H.; Hosny R. | C188: Synthesis and evaluation of novel copper hydroxide-loaded SBA-15 as inhibitors for an oilfield carbonate scale control: an experiment and a model study | D188: 2024 | E188: H2Open Journal | F188: 10.2166/h2oj.2023.076 | G188: v1.1 B1 tightened (354) | H188: R | I188: Copper hydroxide-SBA-15 inhibitors, oilfield carbonate scale control, explicit
A189: U138 | B189: Hashemi S.H.; Besharati Z.; Torabi F.; Pimentel N. | C189: Thermodynamic Prediction of Scale Formation in Oil Fields During Water Injection: Application of SPsim Program Through Utilizing Advanced Visual Basic Excel Tool | D189: 2024 | E189: Processes | F189: 10.3390/pr12122722 | G189: v1.0 Core query (303) | H189: R | I189: Thermodynamic prediction of scale formation, oil fields water injection, SPsim tool
A190: U138 | B190: Hashemi S.H.; Besharati Z.; Torabi F.; Pimentel N. | C190: Thermodynamic Prediction of Scale Formation in Oil Fields During Water Injection: Application of SPsim Program Through Utilizing Advanced Visual Basic Excel Tool | D190: 2024 | E190: Processes | F190: 10.3390/pr12122722 | G190: v1.1 B1 tightened (354) | H190: R | I190: Thermodynamic prediction of scale formation, oil fields water injection, SPsim tool
... A287: U209 | B287: Poletto V.G.; Mazuroski M.E.; de Assis Pereira F.R.; Schwalbert M.P.; Duarte Ferreira M.V.; Torres Eduardo T.H.; De Lai F.C.; de Mello Junqueira S.L.; Martins A.L. | C287: Hydrodynamic Simulation Supports Scale Formation in Technical Specification for Downhole Equipment | D287: 2022 | E287: Society of Petroleum Engineers - SPE International Oilfield Scale Conference and Exhibition, OSS 2022 | F287: 10.2118/209499-MS | G287: v1.1 B1 tightened (354) | H287: R | I287: Hydrodynamic simulation supports scale-formation spec for downhole equipment
A288: U210 | B288: Rostaminikoo E.; Ayatollahi S.; Taghikhani V.; Kalantarian A. | C288: INVESTIGATING THE INHIBITION OF FORMATION DAMAGE DURING LOW SALINITY WATER INJECTION; USING QCM TECHNIQUE | D288: 2022 | E288: 83rd EAGE Conference and Exhibition 2022 | G288: v1.1 B1 tightened (354) | H288: R | I288: Inhibition of formation damage, low salinity water injection QCM, CaSO4 scale
A289: U211 | B289: Nikoo A.H.; Malayeri M.R. | C289: Incorporation of geochemical, geometrical and intermolecular interactions into modelling of scale removal in a capillary microchannel | D289: 2022 | E289: Journal of Petroleum Science and Engineering | F289: 10.1016/j.petrol.2021.109311 | G289: v1.0 Core query (303) | H289: R | I289: Modelling of gypsum scale removal in capillary microchannel, reservoir rocks
A290: U211 | B290: Nikoo A.H.; Malayeri M.R. | C290: Incorporation of geochemical, geometrical and intermolecular interactions into modelling of scale removal in a capillary microchannel | D290: 2022 | E290: Journal of Petroleum Science and Engineering | F290: 10.1016/j.petrol.2021.109311 | G290: v1.1 B1 tightened (354) | H290: R | I290: Modelling of gypsum scale removal in capillary microchannel, reservoir rocks
A291: U212 | B291: Tang X.; Kum S.; Liu H. | C291: Inland Desalination Brine Disposal: A Baseline Study from Southern California on Brine Transport Infrastructure and Treatment Potential | D291: 2022 | E291: ACS ES and T Engineering | F291: 10.1021/acsestengg.1c00276 | G291: v1.0 Core query (303) | H291: M | I291: Inland desalination brine disposal pipeline scaling - municipal, not oilfield
A292: U213 | B292: Paudyal S.; Dai Z.; Dai C.; Ko S.; Wang X.; Li W.; Leschied C. | C292: Introduction of a New BCC Continuous Stirred Tank Reactor Inhibitor BCIn Screening Method for Chemicals in Controlling Inorganic Scales in Oil/Gas Production | D292: 2022 | E292: Society of Petroleum Engineers - SPE International Oilfield Scale Conference and Exhibition, OSS 2022 | F292: 10.2118/209477-MS | G292: v1.0 Core query (303) | H292: R | I292: BCC CSTR inhibitor screening method for inorganic scales, oil/gas production
A293: U213 | B293: Paudyal S.; Dai Z.; Dai C.; Ko S.; Wang X.; Li W.; Leschied C. | C293: Introduction of a New BCC Continuous Stirred Tank Reactor Inhibitor BCIn Screening Method for Chemicals in Controlling Inorganic Scales in Oil/Gas Production | D293: 2022 | E293: Society of Petroleum Engineers - SPE International Oilfield Scale Conference and Exhibition, OSS 2022 | F293: 10.2118/209477-MS | G293: v1.1 B1 tightened (354) | H293: R | I293: BCC CSTR inhibitor screening method for inorganic scales, oil/gas production
A294: U214 | B294: Liu Y.; Dai Z.; Kan A.T.; Tomson M.B.; Zhang P. | C294: Investigation of sorptive interaction between phosphonate inhibitor and barium sulfate for oilfield scale control | D294: 2022 | E294: Journal of Petroleum Science and Engineering | F294: 10.1016/j.petrol.2021.109425 | G294: v1.1 B1 tightened (354) | H294: R | I294: Sorptive interaction phosphonate inhibitor & barium sulfate, oilfield scale control
A295: U215 | B295: Gasimli N.; Mahmoud M.; Kamal M.S.; Patil S.; Alsaiari H.A.; Hussein I.A. | C295: Iron Sulfide Scale Inhibition in Carbonate Reservoirs | D295: 2022 | E295: ACS Omega | F295: 10.1021/acsomega.2c01568 | G295: v1.1 B1 tightened (354) | H295: R | I295: Iron sulfide scale inhibition, carbonate reservoirs, squeeze treatment oilfield
A296: U216 | B296: Wang X.; Dai Z.; Ko S.; Deng G.; Zhao Y.; Dai C.; Li W.; Paudyal S.; Yao X.; Kan A.T.; Tomson M. | C296: Iron Sulfide Solubility Measurement and Modeling over Wide Ranges of Temperatures, Ionic Strength, and pH | D296: 2022 | E296: SPE Journal | F296: 10.2118/208616-PA | G296: v1.0 Core query (303) | H296: M | I296: Iron sulfide solubility measurement/modeling - fundamental, multi-domain
A297: U217 | B297: Sanni O.; Charpentier T.; Harbottle D.; Barker R.; Pessu F.; Neville A. | C297: Kinetics of Transformation and Inhibition of Calcium Carbonate Scale Formation in Mixed Oil Fractions | D297: 2022 | E297: Society of Petroleum Engineers - SPE International Oilfield Scale Conference and Exhibition, OSS 2022 | F297: 10.2118/209515-MS | G297: v1.0 Core query (303) | H297: R | I297: Kinetics of transformation/inhibition of CaCO3 scale, mixed oil fractions pipeline
A298: U217 | B298: Sanni O.; Charpentier T.; Harbottle D.; Barker R.; Pessu F.; Neville A. | C298: Kinetics of Transformation and Inhibition of Calcium Carbonate Scale Formation in Mixed Oil Fractions | D298: 2022 | E298: Society of Petroleum Engineers - SPE International Oilfield Scale Conference and Exhibition, OSS 2022 | F298: 10.2118/209515-MS | G298: v1.1 B1 tightened (354) | H298: R | I298: Kinetics of transformation/inhibition of CaCO3 scale, mixed oil fractions pipeline
A299: U218 | B299: Husna U.Z.; Elraies K.A.; Shuhili J.A.B.M.; Deo Tewari R. | C299: Laboratory Study on the Use of Novel Biodegradable Scale Inhibitors Against Mixed Calcium Carbonate and Calcium Sulfate Scale | D299: 2022 | E299: Offshore Technology Conference Asia, OTCA 2022 | F299: 10.4043/31492-MS | G299: v1.0 Core query (303) | H299: R | I299: Biodegradable SI for mixed CaCO3/CaSO4 scale, oil and gas operation
A300: U218 | B300: Husna U.Z.; Elraies K.A.; Shuhili J.A.B.M.; Deo Tewari R. | C300: Laboratory Study on the Use of Novel Biodegradable Scale Inhibitors Against Mixed Calcium Carbonate and Calcium Sulfate Scale | D300: 2022 | E300: Offshore Technology Conference Asia, OTCA 2022 | F300: 10.4043/31492-MS | G300: v1.1 B1 tightened (354) | H300: R | I300: Biodegradable SI for mixed CaCO3/CaSO4 scale, oil and gas operation
... A310: U226 | B310: Ferrer A.; Bennett B. | C310: Remediating Oilfield Deposition from the Laboratory Bench to the Field - Development of a Multifunctional Product | D310: 2022 | E310: International Petroleum Technology Conference, IPTC 2022 | F310: 10.2523/IPTC-22249-MS | G310: v1.1 B1 tightened (354) | H310: R | I310: Remediating oilfield deposition lab-to-field, iron sulfide/scales, multifunctional
A311: U227 | B311: Bakeev K.; Toprak O.; Lugo-Gonzalez V.; Espinosa F.; Ramirez F.; Danks L.; Zhang A.; Martinez E.; Vargas W. | C311: SCALE INHIBITION IN HIGH SOLIDS SLURRY - FINANCIAL AND PRODUCTION IMPACT IN A GOLD MINE OPERATION | D311: 2022 | E311: Proceedings of the 27th International Mining Congress and Exhibition of Turkey, IMCET 2022 | G311: v1.1 B1 tightened (354) | H311: M | I311: Scale inhibition in high-solids slurry, gold mine operation - mining, not oil/gas
A312: U228 | B312: Perkins L.; Tyree R.; Ondash M.; Kreutzman L. | C312: Scale Remediation in the Marcellus Shale: Calcium Carbonate and Iron Sulfide | D312: 2022 | E312: SPE Eastern Regional Meeting | F312: 10.2118/211870-MS | G312: v1.0 Core query (303) | H312: R | I312: Scale remediation in Marcellus Shale, CaCO3/FeS, explicit
A313: U228 | B313: Perkins L.; Tyree R.; Ondash M.; Kreutzman L. | C313: Scale Remediation in the Marcellus Shale: Calcium Carbonate and Iron Sulfide | D313: 2022 | E313: SPE Eastern Regional Meeting | F313: 10.2118/211870-MS | G313: v1.1 B1 tightened (354) | H313: R | I313: Scale remediation in Marcellus Shale, CaCO3/FeS, explicit
A314: U229 | B314: Moh D.Y.; Zhang H.; Wang S.; Yin X.; Qiao R. | C314: Soaking in CO2 huff-n-puff: A single-nanopore scale study | D314: 2022 | E314: Fuel | F314: 10.1016/j.fuel.2021.122026 | G314: v1.0 Core query (303) | H314: I | I314: CO2 huff-n-puff molecular dynamics in nanopore - fundamental, no scale focus
A315: U230 | B315: Okocha C.; Thornton A.; Wylde J. | C315: Squeeze Deployed Sulfide Inhibitor Successfully Averts Challenging Sulfide Scale Deposition in Permian and Williston Unconventional Basins | D315: 2022 | E315: Society of Petroleum Engineers - ADIPEC 2022 | F315: 10.2118/211126-MS | G315: v1.0 Core query (303) | H315: R | I315: Squeeze-deployed sulfide inhibitor, Permian/Williston unconventional basins
A316: U230 | B316: Okocha C.; Thornton A.; Wylde J. | C316: Squeeze Deployed Sulfide Inhibitor Successfully Averts Challenging Sulfide Scale Deposition in Permian and Williston Unconventional Basins | D316: 2022 | E316: Society of Petroleum Engineers - ADIPEC 2022 | F316: 10.2118/211126-MS | G316: v1.1 B1 tightened (354) | H316: R | I316: Squeeze-deployed sulfide inhibitor, Permian/Williston unconventional basins
A317: U231 | B317: Ismail N.; Alshami A.S.; Hussein I.A. | C317: Synthesis and evaluation of a novel polyacrylamide functionalized nano-silica as a calcium carbonate inhibitor in upstream applications | D317: 2022 | E317: Journal of Petroleum Science and Engineering | F317: 10.1016/j.petrol.2021.109864 | G317: v1.1 B1 tightened (354) | H317: R | I317: Polyacrylamide nano-silica CaCO3 inhibitor, upstream applications, explicit
A318: U232 | B318: Talebi S.; Riahi S.; Rostami B. | C318: The Effect of Blending Polymeric and Phosphonate Scale Inhibitors on Fluid/Fluid and Rock/Fluid Interactions: A Comprehensive Experimental and Theoretical Study | D318: 2022 | E318: SPE Journal | F318: 10.2118/210583-PA | G318: v1.0 Core query (303) | H318: R | I318: Blending polymeric/phosphonate SI, fluid/rock interactions, oil formations
A319: U232 | B319: Talebi S.; Riahi S.; Rostami B. | C319: The Effect of Blending Polymeric and Phosphonate Scale Inhibitors on Fluid/Fluid and Rock/Fluid Interactions: A Comprehensive Experimental and Theoretical Study | D319: 2022 | E319: SPE Journal | F319: 10.2118/210583-PA | G319: v1.1 B1 tightened (354) | H319: R | I319: Blending polymeric/phosphonate SI, fluid/rock interactions, oil formations
A320: U233 | B320: Heath S.; Mackay E.; Bagala S. | C320: The Future of Scale Control – The Impact of Net Zero | D320: 2022 | E320: Society of Petroleum Engineers - SPE International Oilfield Scale Conference and Exhibition, OSS 2022 | F320: 10.2118/209492-MS | G320: v1.0 Core query (303) | H320: R | I320: Future of scale control and net-zero impact, oil and gas wells, explicit
A321: U233 | B321: Heath S.; Mackay E.; Bagala S. | C321: The Future of Scale Control – The Impact of Net Zero | D321: 2022 | E321: Society of Petroleum Engineers - SPE International Oilfield Scale Conference and Exhibition, OSS 2022 | F321: 10.2118/209492-MS | G321: v1.1 B1 tightened (354) | H321: R | I321: Future of scale control and net-zero impact, oil and gas wells, explicit
A322: U234 | B322: Ness G.; Sorbie K.S.; Al Mesmari A.H.; Masalmeh S. | C322: The Impact of CCUS for Improved Oil Recovery on CaCO3 Scaling Potential of Produced Fluids | D322: 2022 | E322: Society of Petroleum Engineers - SPE EuropEC - Europe Energy Conference featured at the 83rd EAGE Annual Conference and Exhibition, EURO 2022 | F322: 10.2118/209676-MS | G322: v1.1 B1 tightened (354) | H322: R | I322: CCUS-EOR impact on CaCO3 scaling potential of produced fluids, explicit
A323: U235 | B323: Kaasa B.; Somme B.; MacDonald R.; Kjørsvik K.; Saunes A.; Heath S.; Stamnes M. | C323: The Oda Field: From Scale Prediction to Reality - Why Squeezing was Not Necessary Despite a High Calcium Sulphate Risk | D323: 2022 | E323: Society of Petroleum Engineers - SPE International Oilfield Scale Conference and Exhibition, OSS 2022 | F323: 10.2118/209507-MS | G323: v1.0 Core query (303) | H323: R | I323: Oda field scale prediction vs reality, CaSO4 squeeze, subsea well, explicit
... A337: U244 | B337: Tranter M.; De Lucia M.; Kühn M. | C337: Barite scaling potential modelled for fractured-porous geothermal reservoirs | D337: 2021 | E337: Minerals | F337: 10.3390/min11111198 | G337: v1.1 B1 tightened (354) | H337: M | I337: Barite scaling modelled, fractured-porous geothermal reservoirs - geothermal
...

Sheet Metrics
A1: Pilot Classification Metrics
A2: Auto-calculated from the 'RMI Classification' tab — do not edit these cells directly.
A4: Query Source | B4: R | C4: M | D4: I | E4: Total Tagged | F4: Direct Relevance % (R/Total) | G4: Coverage % ((R+M)/Total)
A5: v1.0 Core query (303) | B5: =COUNTIFS('RMI Classification'!$G:$G,$A5,'RMI Classification'!$H:$H,"R") -> 238 | C5: =COUNTIFS('RMI Classification'!$G:$G,$A5,'RMI Classification'!$H:$H,"M") -> 41 | D5: =COUNTIFS('RMI Classification'!$G:$G,$A5,'RMI Classification'!$H:$H,"I") -> 25 | E5: =SUM(B5:D5) -> 304 | F5: =IFERROR(B5/E5,"-") -> 0.78289474 | G5: =IFERROR((B5+C5)/E5,"-") -> 0.91776316
A6: v1.1 B1 tightened (354) | B6: =COUNTIFS('RMI Classification'!$G:$G,$A6,'RMI Classification'!$H:$H,"R") -> 311 | C6: =COUNTIFS('RMI Classification'!$G:$G,$A6,'RMI Classification'!$H:$H,"M") -> 34 | D6: =COUNTIFS('RMI Classification'!$G:$G,$A6,'RMI Classification'!$H:$H,"I") -> 9 | E6: =SUM(B6:D6) -> 354 | F6: =IFERROR(B6/E6,"-") -> 0.87853107 | G6: =IFERROR((B6+C6)/E6,"-") -> 0.97457627
A7: B2 (570) | B7: =COUNTIFS('RMI Classification'!$G:$G,$A7,'RMI Classification'!$H:$H,"R") -> 0 | C7: =COUNTIFS('RMI Classification'!$G:$G,$A7,'RMI Classification'!$H:$H,"M") -> 0 | D7: =COUNTIFS('RMI Classification'!$G:$G,$A7,'RMI Classification'!$H:$H,"I") -> 0 | E7: =SUM(B7:D7) -> 0 | F7: =IFERROR(B7/E7,"-") -> - | G7: =IFERROR((B7+C7)/E7,"-") -> -
A8: IEEE Block D (18) | B8: =COUNTIFS('RMI Classification'!$G:$G,$A8,'RMI Classification'!$H:$H,"R") -> 5 | C8: =COUNTIFS('RMI Classification'!$G:$G,$A8,'RMI Classification'!$H:$H,"M") -> 3 | D8: =COUNTIFS('RMI Classification'!$G:$G,$A8,'RMI Classification'!$H:$H,"I") -> 10 | E8: =SUM(B8:D8) -> 18 | F8: =IFERROR(B8/E8,"-") -> 0.27777778 | G8: =IFERROR((B8+C8)/E8,"-") -> 0.44444444
A9: IEEE Block E (5) | B9: =COUNTIFS('RMI Classification'!$G:$G,$A9,'RMI Classification'!$H:$H,"R") -> 2 | C9: =COUNTIFS('RMI Classification'!$G:$G,$A9,'RMI Classification'!$H:$H,"M") -> 1 | D9: =COUNTIFS('RMI Classification'!$G:$G,$A9,'RMI Classification'!$H:$H,"I") -> 2 | E9: =SUM(B9:D9) -> 5 | F9: =IFERROR(B9/E9,"-") -> 0.4 | G9: =IFERROR((B9+C9)/E9,"-") -> 0.6
A10: IEEE Block F (13) | B10: =COUNTIFS('RMI Classification'!$G:$G,$A10,'RMI Classification'!$H:$H,"R") -> 5 | C10: =COUNTIFS('RMI Classification'!$G:$G,$A10,'RMI Classification'!$H:$H,"M") -> 2 | D10: =COUNTIFS('RMI Classification'!$G:$G,$A10,'RMI Classification'!$H:$H,"I") -> 6 | E10: =SUM(B10:D10) -> 13 | F10: =IFERROR(B10/E10,"-") -> 0.38461538 | G10: =IFERROR((B10+C10)/E10,"-") -> 0.53846154
A11: IEEE Block G (11) | B11: =COUNTIFS('RMI Classification'!$G:$G,$A11,'RMI Classification'!$H:$H,"R") -> 1 | C11: =COUNTIFS('RMI Classification'!$G:$G,$A11,'RMI Classification'!$H:$H,"M") -> 3 | D11: =COUNTIFS('RMI Classification'!$G:$G,$A11,'RMI Classification'!$H:$H,"I") -> 7 | E11: =SUM(B11:D11) -> 11 | F11: =IFERROR(B11/E11,"-") -> 0.090909091 | G11: =IFERROR((B11+C11)/E11,"-") -> 0.36363636
A12: WoS frozen (192) | B12: =COUNTIFS('RMI Classification'!$G:$G,$A12,'RMI Classification'!$H:$H,"R") -> 158 | C12: =COUNTIFS('RMI Classification'!$G:$G,$A12,'RMI Classification'!$H:$H,"M") -> 24 | D12: =COUNTIFS('RMI Classification'!$G:$G,$A12,'RMI Classification'!$H:$H,"I") -> 10 | E12: =SUM(B12:D12) -> 192 | F12: =IFERROR(B12/E12,"-") -> 0.82291667 | G12: =IFERROR((B12+C12)/E12,"-") -> 0.94791667
A13: ScienceDirect (2) | B13: =COUNTIFS('RMI Classification'!$G:$G,$A13,'RMI Classification'!$H:$H,"R") -> 2 | C13: =COUNTIFS('RMI Classification'!$G:$G,$A13,'RMI Classification'!$H:$H,"M") -> 0 | D13: =COUNTIFS('RMI Classification'!$G:$G,$A13,'RMI Classification'!$H:$H,"I") -> 0 | E13: =SUM(B13:D13) -> 2 | F13: =IFERROR(B13/E13,"-") -> 1 | G13: =IFERROR((B13+C13)/E13,"-") -> 1
A14: Saudi Digital Library (59) | B14: =COUNTIFS('RMI Classification'!$G:$G,$A14,'RMI Classification'!$H:$H,"R") -> 54 | C14: =COUNTIFS('RMI Classification'!$G:$G,$A14,'RMI Classification'!$H:$H,"M") -> 3 | D14: =COUNTIFS('RMI Classification'!$G:$G,$A14,'RMI Classification'!$H:$H,"I") -> 2 | E14: =SUM(B14:D14) -> 59 | F14: =IFERROR(B14/E14,"-") -> 0.91525424 | G14: =IFERROR((B14+C14)/E14,"-") -> 0.96610169
A15: OVERALL (all tagged records) | B15: =COUNTIF('RMI Classification'!$H:$H,"R") -> 776 | C15: =COUNTIF('RMI Classification'!$H:$H,"M") -> 111 | D15: =COUNTIF('RMI Classification'!$H:$H,"I") -> 71 | E15: =SUM(B15:D15) -> 958 | F15: =IFERROR(B15/E15,"-") -> 0.81002088 | G15: =IFERROR((B15+C15)/E15,"-") -> 0.92588727
A18: Decision guide: direct relevance below ~30–40% usually means the query is too broad. Scopus, WoS and ScienceDirect are all high-relevance primary/supplementary sources; IEEE is a low-relevance supplementary source (expected, narrow domain fit). ScienceDirect's small N reflects its Elsevier-only coverage, not a search-quality problem.
A33: PRISMA 2020 TRACKING
A35: IDENTIFICATION
A36: Records identified — Scopus (frozen query) | B36: 354
A37: Records identified — Web of Science | B37: 192
A38: Records identified — IEEE Xplore (4 sub-searches, deduped) | B38: 27
A39: Records identified — ScienceDirect (2 sub-searches, deduped) | B39: 2
A40: Records identified — Saudi Digital Library (SDL) (59 results, 38 already in corpus) | B40: 59
A41: Total raw records identified (all databases) | B41: 634
A42: Duplicates removed | B42: 174
A44: SCREENING (title/abstract)
A45: Records screened (= Master Corpus) | B45: 460
A46: Records excluded at title/abstract stage | B46: 30
A47: — Non-substantive record (book TOC/chapter/index) | B47: 9
A48: — Outside domain (unrelated field) | B48: 8
A49: — Pure corrosion study (no scale-formation component) | B49: 4
A50: — Different phenomenon (not flow-assurance mineral scale) | B50: 4
A51: — Unrelated industry (non-oilfield application) | B51: 4
A52: — Retracted publication | B52: 1
A54: ELIGIBILITY (full-text)
A55: Reports sought for retrieval (R+M proceeding) | B55: 430
A56: Reports not retrieved
A57: Full-text reports assessed for eligibility
A58: Full-text reports excluded, with reasons
A60: INCLUDED
A61: Studies included in the final systematic review

Sheet Master Corpus
A1: Master Corpus — Prioritized Full-Text Reading Queue
A2: 439 records, sorted into your reading queue: Tier 1 (M-tagged, resolve first) → Tier 2 (R-tagged, confirm eligibility) → Tier 3 (Excluded, no action needed), each tier ranked by Citation Velocity (citations ÷ years since publication — balances influence against recency). Columns N–P are blank for your full-text screening — blue text = your input cells.
A4: Priority Rank | B4: Reading Tier | C4: Record ID | D4: Authors | E4: Title | F4: Year | G4: Venue | H4: DOI | I4: Source DB(s) | J4: Pilot Tag | K4: Citations | L4: Citation Velocity | M4: Screening Decision | N4: Exclusion Category | O4: Full-text Retrieved? (Y/N) | P4: Full-text Decision (Include/Exclude) | Q4: Full-text Exclusion Reason
A5: 1 | B5: 1 - Maybe (resolve first) | C5: M0173 | D5: Jew, AD; Druhan, JL; Ihme, M; Kovscek, AR; Battiato, I; Kaszuba, JP; Bargar, JR; Brown, GE | E5: Chemical and Reactive Transport Processes Associated with Hydraulic Fracturing of Unconventional Oil/Gas Shales | F5: 2022 | G5: CHEMICAL REVIEWS | H5: 10.1021/acs.chemrev.1c00504 | I5: WoS | J5: M | K5: 90 | L5: 18 | M5: Included — proceed to full-text
A6: 2 | B6: 1 - Maybe (resolve first) | C6: M0153 | D6: Wang M.; Tan M.Y.; Zhu Y.; Huang Y.; Xu Y. | E6: Probing top-of-the-line corrosion using coupled multi-electrode array in conjunction with local electrochemical measurement | F6: 2023 | G6: npj Materials Degradation | H6: 10.1038/s41529-023-00332-x | I6: Scopus;WoS | J6: M | K6: 29 | L6: 7.25 | M6: Included — proceed to full-text
A7: 3 | B7: 1 - Maybe (resolve first) | C7: M0420 | D7: Zhen-Wu, BY; Dideriksen, K; Olsson, J; Raahauge, PJ; Stipp, SLS; Oelkers, EH | E7: Experimental determination of barite dissolution and precipitation rates as a function of temperature and aqueous fluid composition | F7: 2016 | G7: GEOCHIMICA ET COSMOCHIMICA ACTA | H7: 10.1016/j.gca.2016.08.041 | I7: WoS | J7: M | K7: 78 | L7: 7.09 | M7: Included — proceed to full-text
A8: 4 | B8: 1 - Maybe (resolve first) | C8: M0324 | D8: Oshchepkov M.; Kamagurov S.; Tkachenko S.; Ryabova A.; Popov K. | E8: Insight into the Mechanisms of Scale Inhibition: A Case Study of a Task-Specific Fluorescent-Tagged Scale Inhibitor Location on Gypsum Crystals | F8: 2019 | G8: ChemNanoMat | H8: 10.1002/cnma.201800660 | I8: Scopus;WoS | J8: M | K8: 55 | L8: 6.88 | M8: Included — proceed to full-text
A9: 5 | B9: 1 - Maybe (resolve first) | C9: M0245 | D9: Spinthaki A.; Kamaratou M.; Skordalou G.; Petratos G.; Petrou I.; Tramaux A.; David G.; Demadis K.D. | E9: Searching for a universal scale inhibitor: A multi-scale approach towards inhibitor efficiency | F9: 2021 | G9: Geothermics | H9: 10.1016/j.geothermics.2020.101954 | I9: Scopus | J9: M | K9: 37 | L9: 6.17 | M9: Included — proceed to full-text
A10: 6 | B10: 1 - Maybe (resolve first) | C10: M0106 | D10: Ebrahimi, M; Deymi, O; Hadavimoghaddam, F; Hemmati-Sarapardeh, A | E10: Modeling gypsum (calcium sulfate dihydrate) solubility in aqueous electrolyte solutions using extreme learning machine | F10: 2024 | G10: JOURNAL OF WATER PROCESS ENGINEERING | H10: 10.1016/j.jwpe.2023.104664 | I10: WoS | J10: M | K10: 18 | L10: 6 | M10: Included — proceed to full-text
A11: 7 | B11: 1 - Maybe (resolve first) | C11: M0301 | D11: Popov K.; Oshchepkov M.; Afanas'eva E.; Koltinova E.; Dikareva Y.; Rönkkömäki H. | E11: A new insight into the mechanism of the scale inhibition: DLS study of gypsum nucleation in presence of phosphonates using nanosilver dispersion as an internal light scattering intensity reference | F11: 2019 | G11: Colloids and Surfaces A: Physicochemical and Engineering Aspects | H11: 10.1016/j.colsurfa.2018.10.015 | I11: Scopus;WoS | J11: M | K11: 45 | L11: 5.62 | M11: Included — proceed to full-text
A12: 8 | B12: 1 - Maybe (resolve first) | C12: M0239 | D12: Khasani; Deendarlianto; Itoi R. | E12: Numerical study of the effects of CO2 gas in geothermal water on the fluid-flow characteristics in production wells | F12: 2021 | G12: Engineering Applications of Computational Fluid Mechanics | H12: 10.1080/19942060.2020.1862709 | I12: Scopus;WoS | J12: M | K12: 30 | L12: 5 | M12: Included — proceed to full-text
A13: 9 | B13: 1 - Maybe (resolve first) | C13: M0089 | D13: Hong, H; Ye, TC; Zhang, J; Wang, ZM | E13: Corrosion mitigation behavior of mild steel in supercritical CO2 environments with varying the solution volume | F13: 2024 | G13: CORROSION SCIENCE | H13: 10.1016/j.corsci.2024.111853 | I13: WoS | J13: M | K13: 12 | L13: 4 | M13: Included — proceed to full-text
A14: 10 | B14: 1 - Maybe (resolve first) | C14: M0088 | D14: Wang L.-C.; Che Y.; Zhu Y.-R.; Guo S.-L.; Ma W.; Zhao Q.-L.; Li G.; Wang L.-B. | E14: Comparative study of a low phosphorous co-polymer inhibitor with commercial scale inhibitors used in cooling water systems | F14: 2024 | G14: Journal of Applied Polymer Science | H14: 10.1002/app.55145 | I14: Scopus;WoS | J14: M | K14: 11 | L14: 3.67 | M14: Included — proceed to full-text
A15: 11 | B15: 1 - Maybe (resolve first) | C15: M0330 | D15: Sojoudi, H; Nemani, SK; Mullin, KM; Wilson, MG; Aladwani, H; Lababidi, H; Gleason, KK | E15: Micro-/Nanoscale Approach for Studying Scale Formation and Developing Scale-Resistant Surfaces | F15: 2019 | G15: ACS APPLIED MATERIALS & INTERFACES | H15: 10.1021/acsami.8b18523 | I15: WoS | J15: M | K15: 27 | L15: 3.38 | M15: Included — proceed to full-text
A16: 12 | B16: 1 - Maybe (resolve first) | C16: M0217 | D16: Mankikar T.Y. | E16: Comparison of indices for scaling and corrosion tendency of groundwater: Case study of unconfined aquifer from Mahoba District, U.P. State | F16: 2021 | G16: Applied Water Science | H16: 10.1007/s13201-021-01423-3 | I16: Scopus | J16: M | K16: 20 | L16: 3.33 | M16: Included — proceed to full-text
... A31: 27 | B31: 1 - Maybe (resolve first) | C31: M0276 | D31: Al Nasser W.; Al Jeshi Y. | E31: Inline technique to evaluate the performance of scale inhibitors for calcium carbonate scale aggregation and prevention | F31: 2020 | G31: Chemical Engineering Research and Design | H31: 10.1016/j.cherd.2020.02.012 | I31: Scopus | J31: M | K31: 5 | L31: 0.71 | M31: Included — proceed to full-text
A32: 28 | B32: 1 - Maybe (resolve first) | C32: M0377 | D32: AlShamaileh, E; AlRawajfeh, A; AlMa'abrah, A | E32: ASSESSMENT OF OF QUALITY AND POTENTIAL OF SCALE FORMATION AND CORROSIVITY OF DRINKING WATER SUPPLIED FROM DISI TO AMMAN, JORDAN | F32: 2017 | G32: FRESENIUS ENVIRONMENTAL BULLETIN | I32: WoS | J32: M | K32: 7 | L32: 0.7 | M32: Included — proceed to full-text
A33: 29 | B33: 1 - Maybe (resolve first) | C33: M0380 | D33: Mazziotti di Celso G.; Prisciandaro M.; Karatza D.; Lancia A.; Musmarra D. | E33: Calcium carbonate scales on process equipment: A measure of the induction time for nucleation | F33: 2017 | G33: Desalination and Water Treatment | H33: 10.5004/dwt.2017.20300 | I33: Scopus;WoS | J33: M | K33: 7 | L33: 0.7 | M33: Included — proceed to full-text
A34: 30 | B34: 1 - Maybe (resolve first) | C34: M0076 | D34: A. A. Litvinenko; Y. V. Vankov; A. R. Timershin; D. E. Sharafiev; R. A. Ponomarev | E34: The Method of Obtaining Deposits on the Heat Exchange Surface of Heat Exchangers | F34: 2025 | G34: 2025 7th International Youth Conference on Radio Electronics, Electrical and Power Engineering (REEPE) | H34: 10.1109/REEPE63962.2025.10970875 | I34: IEEE | J34: M | K34: 1 | L34: 0.5 | M34: Included — proceed to full-text
A35: 31 | B35: 1 - Maybe (resolve first) | C35: M0225 | D35: Lü, Y; Lu, K; Bai, YX; Ma, YL; Ren, YS | E35: Fouling characteristics of 90° elbow in high salinity wastewater from coal chemical industry | F35: 2021 | G35: CHINESE JOURNAL OF CHEMICAL ENGINEERING | H35: 10.1016/j.cjche.2020.09.034 | I35: WoS | J35: M | K35: 3 | L35: 0.5 | M35: Included — proceed to full-text
A36: 32 | B36: 1 - Maybe (resolve first) | C36: M0328 | D36: Al-Maabreh, AM; Al-Rawajfeh, AE; Alshamaileh, E; Al-Bazedi, GA | E36: MITIGATION OF SCALE PROBLEM IN THE PUMPED DISI WATER TO AMMAN, JORDAN | F36: 2019 | G36: ENVIRONMENT PROTECTION ENGINEERING | H36: 10.5277/epe190108 | I36: WoS | J36: M | K36: 4 | L36: 0.5 | M36: Included — proceed to full-text
A37: 33 | B37: 1 - Maybe (resolve first) | C37: M0435 | D37: Cavazza M. | E37: Reducing Freshwater Consumption in the Marcellus Shale Play by Recycling Flowback with Acid Mine Drainage | F37: 2016 | G37: SPE Annual Technical Conference Proceedings | H37: 10.2118/184499-STU | I37: Scopus | J37: M | K37: 5 | L37: 0.45 | M37: Included — proceed to full-text
A38: 34 | B38: 1 - Maybe (resolve first) | C38: M0129 | D38: Heath S.; Mackay E.; Jarrahian K.; Ishkov O.; Gusmao P. | E38: Understanding the Role of Scale Management in Carbon Capture, Utilisation and Storage (CCUS) | F38: 2024 | G38: Society of Petroleum Engineers - SPE Oilfield Scale Symposium, OSS 2024 | H38: 10.2118/218722-MS | I38: Scopus | J38: M | K38: 1 | L38: 0.33 | M38: Included — proceed to full-text
A39: 35 | B39: 1 - Maybe (resolve first) | C39: M0226 | D39: Gonzalez, AH; Frankel, G; Vera, J; Durnie, W; Woollam, R | E39: Galvanic Interactions Between Fe Electrodes in CO2-Saturated Solutions with Different pH | F39: 2021 | G39: CORROSION | H39: 10.5006/3556 | I39: WoS | J39: M | K39: 2 | L39: 0.33 | M39: Included — proceed to full-text
A40: 36 | B40: 1 - Maybe (resolve first) | C40: M0427 | D40: Gill J.S.; Jacobs G.T.; Butler S. | E40: Mitigation of calcium sulfate scaling in geothermal production wells | F40: 2016 | G40: Transactions - Geothermal Resources Council | I40: Scopus | J40: M | K40: 3 | L40: 0.27 | M40: Included — proceed to full-text
A41: 37 | B41: 1 - Maybe (resolve first) | C41: M0216 | D41: Rodriguez E.; Johnson A.; Porras E.; Xicará J.; Acuña F. | E41: Calcium carbonate inhibition at orzunil geothermal field | F41: 2021 | G41: Transactions - Geothermal Resources Council | I41: Scopus | J41: M | K41: 1 | L41: 0.17 | M41: Included — proceed to full-text
A42: 38 | B42: 1 - Maybe (resolve first) | C42: M0401 | D42: Shady M.; Okafor C.; Pazzi J.; Thomas O.; Sule A.; Ali A.M.; Hamdane T.; Hachelaf H.; Allal A.; Collela L.; Latronico R.; Marfella F. | E42: Reviving a fractured water injection well: The first use of clay acid stimulation in a major oil field in Algeria | F42: 2017 | G42: SPE Middle East Oil and Gas Show and Conference, MEOS, Proceedings | H42: 10.2118/183742-ms | I42: Scopus | J42: M | K42: 1 | L42: 0.1 | M42: Included — proceed to full-text
A43: 39 | B43: 1 - Maybe (resolve first) | C43: M0010 | D43: Yoo S.; Ueda A.; Ozawa A.; Kusakabe Y.; Hiroki M.; Ohkawa M.; Tanikawa S. | E43: Environmental impact assessment of seal water systems during construction of rock cavern tanks at the Namikata National LPG stockpiling base: Characterization of scale deposition using scale surveys and column flow tests | F43: 2026 | G43: Applied Geochemistry | H43: 10.1016/j.apgeochem.2026.106868 | I43: Scopus | J43: M | K43: 0 | L43: 0 | M43: Included — proceed to full-text
A44: 40 | B44: 1 - Maybe (resolve first) | C44: M0019 | D44: Correa-Muñoz E.; Butto-Miranda N.; Parra-Muñoz N.; Díaz-Soler F.; Yazdani-Pedram M.; Neira-Carrillo A. | E44: Nanoscale control of CaCO₃ crystallization by sulfonated polyetherimide nanoparticles investigated via automatic potentiometric titration | F44: 2026 | G44: Journal of Environmental Chemical Engineering | H44: 10.1016/j.jece.2026.122084 | I44: Scopus;WoS | J44: M | K44: 0 | L44: 0 | M44: Included — proceed to full-text
A45: 41 | B45: 1 - Maybe (resolve first) | C45: M0020 | D45: M. Tohara; K. Okuma; Y. Gotoh | E45: Non-Contact Measurement of Non-Metallic Scale Thickness on the Back Side of Ferromagnetic Materials Using Electromagnetic Force–Induced Vibration | F45: 2026 | G45: IEEE Transactions on Magnetics | H45: 10.1109/TMAG.2026.3695830 | I45: IEEE | J45: M | K45: 0 | L45: 0 | M45: Included — proceed to full-text
A46: 42 | B46: 1 - Maybe (resolve first) | C46: M0036 | D46: Abdelaal A.T.; El-Makaty F.M.; Kelland M.A.; Mady M.F. | E46: Surface-engineered magnetic nanoparticles with carboxymethyl inulin coating for interface-controlled mineral scale inhibition | F46: 2026 | G46: Particuology | H46: 10.1016/j.partic.2026.05.004 | I46: Scopus;WoS | J46: M | K46: 0 | L46: 0 | M46: Included — proceed to full-text
A47: 43 | B47: 1 - Maybe (resolve first) | C47: M0038 | D47: M. I. Iqbal; V. K. Kudapa | E47: 18 Injection Water Treatment | F47: 2025 | G47: Oil Well Production Mechanism: Training Manual on Well Production Operations for Non-production Engineers (Oil and Gas Production Operations) | I47: IEEE | J47: M | K47: 0 | L47: 0 | M47: Included — proceed to full-text
A48: 44 | B48: 1 - Maybe (resolve first) | C48: M0068 | D48: Al-Salal M.; Al-Mass S.; Al-Abbasi K.; Kakade S.; Boareki N.; Al-Rashedi H.; Dashti B.; Karadi N.; Munck D.; Madsen T.; Lydersen M. | E48: Pioneering Advanced Ceramic Water Filtration Compact Skids for Efficient Water Injection in Tight Reservoirs: A Successful Pilot in Abduliyah Field | F48: 2025 | G48: Society of Petroleum Engineers - ADIPEC 2025 | H48: 10.2118/230135-MS | I48: Scopus | J48: M | K48: 0 | L48: 0 | M48: Included — proceed to full-text
A49: 45 | B49: 1 - Maybe (resolve first) | C49: M0177 | D49: J. Boguniewicz-Zablocka; P. Danisz; R. Gono | E49: Evaluation of Water Quality Influence on Power Plant Cooling System | F49: 2022 | G49: 2022 22nd International Scientific Conference on Electric Power Engineering (EPE) | H49: 10.1109/EPE54603.2022.9814150 | I49: IEEE | J49: M | K49: 0 | L49: 0 | M49: Included — proceed to full-text
A50: 46 | B50: 1 - Maybe (resolve first) | C50: M0197 | D50: Bakeev K.; Toprak O.; Lugo-Gonzalez V.; Espinosa F.; Ramirez F.; Danks L.; Zhang A.; Martinez E.; Vargas W. | E50: SCALE INHIBITION IN HIGH SOLIDS SLURRY - FINANCIAL AND PRODUCTION IMPACT IN A GOLD MINE OPERATION | F50: 2022 | G50: Proceedings of the 27th International Mining Congress and Exhibition of Turkey, IMCET 2022 | I50: Scopus | J50: M | K50: 0 | L50: 0 | M50: Included — proceed to full-text
A51: 47 | B51: 1 - Maybe (resolve first) | C51: M0224 | D51: Neerup R.; Figueroa-Murcia C.; Løge I.A.; Fosbøl P.L. | E51: FeCO3 mineralization and solubility - a guiding factor CO2 corrosion and storage | F51: 2021 | G51: 15th Greenhouse Gas Control Technologies Conference 2021, GHGT 2021 | I51: Scopus | J51: M | K51: 0 | L51: 0 | M51: Included — proceed to full-text
A52: 48 | B52: 1 - Maybe (resolve first) | C52: M0231 | D52: G. Marin; A. Akhmetshin; A. Shubina | E52: Improving the Efficiency of the Combined Recycle Cooling System of Medium-power Combined Cycle Power Units | F52: 2021 | G52: 2021 3rd International Conference on Control Systems, Mathematical Modeling, Automation and Energy Efficiency (SUMMA) | H52: 10.1109/SUMMA53307.2021.9632157 | I52: IEEE | J52: M | K52: 0 | L52: 0 | M52: Included — proceed to full-text
A53: 49 | B53: 1 - Maybe (resolve first) | C53: M0242 | D53: Ramachandran S.; Schorling P.; Mok W.; Liu Z.; Menendez C.; Stewart-Ayala J.; McCabe B.; Klapper H.S. | E53: Prevention and mitigation of scaling and corrosion using corrosion and scale inhibitors | F53: 2021 | G53: Transactions - Geothermal Resources Council | I53: Scopus | J53: M | K53: 0 | L53: 0 | M53: Included — proceed to full-text
A54: 50 | B54: 1 - Maybe (resolve first) | C54: M0263 | D54: Wibisono; F. R. Ningsih; P. Sidauruk; S. K. Wijaya | E54: Design and Implementation of a Fan Beam Tomography System for The Performance Evaluation of Geothermal Pipe | F54: 2020 | G54: 2020 International Conference on Sustainable Energy Engineering and Application (ICSEEA) | H54: 10.1109/ICSEEA50711.2020.9306184 | I54: IEEE | J54: M | K54: 0 | L54: 0 | M54: Included — proceed to full-text
A55: 51 | B55: 1 - Maybe (resolve first) | C55: M0387 | D55: Nusiaputra Y.; Dimier A.D.; Nitschke F.N.; Gaucher E.G.; Kohl T.K. | E55: Effect of flow and physical parameters on the mineral deposition of geothermal wellbores: WellboreKit development | F55: 2017 | G55: 79th EAGE Conference and Exhibition 2017 | H55: 10.3997/2214-4609.201701326 | I55: Scopus | J55: M | K55: 0 | L55: 0 | M55: Included — proceed to full-text
A56: 52 | B56: 1 - Maybe (resolve first) | C56: M0442 | D56: Michael A. Reynolds | E56: What crystal engineering can teach us about water treatment | F56: 2025 | G56: Structural Dynamics | H56: 10.1063/4.0001086 | I56: SDL | J56: M | K56: 0 | L56: 0 | M56: Included — proceed to full-text
A57: 53 | B57: 2 - Relevant (confirm eligibility) | C57: M0348 | D57: Barker, R; Burkle, D; Charpentier, T; Thompson, H; Neville, A | E57: A review of iron carbonate (FeCO3) formation in the oil and gas industry | F57: 2018 | G57: CORROSION SCIENCE | H57: 10.1016/j.corsci.2018.07.021 | I57: WoS | J57: R | K57: 196 | L57: 21.78 | M57: Included — proceed to full-text
A58: 54 | B58: 2 - Relevant (confirm eligibility) | C58: M0046 | D58: Khormali, A; Ahmadi, S; Aleksandrov, AN | E58: Analysis of reservoir rock permeability changes due to solid precipitation during waterflooding using artificial neural network | F58: 2025 | G58: JOURNAL OF PETROLEUM EXPLORATION AND PRODUCTION TECHNOLOGY | H58: 10.1007/s13202-024-01898-1 | I58: WoS | J58: R | K58: 43 | L58: 21.5 | M58: Included — proceed to full-text
A59: 55 | B59: 2 - Relevant (confirm eligibility) | C59: M0096 | D59: Hussein M.F.; Mubarak M.F.; Al-Sirhani A.M.; Hosny R. | E59: Examining the factors that impact the formation of barite scale in water injection operations: experimental study and quantification of scale formation | F59: 2024 | G59: Discover Applied Sciences | H59: 10.1007/s42452-024-06176-7 | I59: Scopus | J59: R | K59: 64 | L59: 21.33 | M59: Included — proceed to full-text
A60: 56 | B60: 2 - Relevant (confirm eligibility) | C60: M0395 | D60: Paukert Vankeuren A.N.; Hakala J.A.; Jarvis K.; Moore J.E. | E60: Mineral Reactions in Shale Gas Reservoirs: Barite Scale Formation from Reusing Produced Water As Hydraulic Fracturing Fluid | F60: 2017 | G60: Environmental Science and Technology | H60: 10.1021/acs.est.7b01979 | I60: Scopus | J60: R | K60: 149 | L60: 14.9 | M60: Included — proceed to full-text
A61: 57 | B61: 2 - Relevant (confirm eligibility) | C61: M0437 | D61: Vazirian M.M.; Charpentier T.V.J.; de Oliveira Penna M.; Neville A. | E61: Surface inorganic scale formation in oil and gas industry: As adhesion and deposition processes | F61: 2016 | G61: Journal of Petroleum Science and Engineering | H61: 10.1016/j.petrol.2015.11.005 | I61: Scopus;WoS | J61: R | K61: 148 | L61: 13.45 | M61: Included — proceed to full-text
A62: 58 | B62: 2 - Relevant (confirm eligibility) | C62: M0369 | D62: De Motte R.A.; Barker R.; Burkle D.; Vargas S.M.; Neville A. | E62: The early stages of FeCO3 scale formation kinetics in CO2 corrosion | F62: 2018 | G62: Materials Chemistry and Physics | H62: 10.1016/j.matchemphys.2018.04.077 | I62: Scopus;WoS | J62: R | K62: 102 | L62: 11.33 | M62: Included — proceed to full-text
A63: 59 | B63: 2 - Relevant (confirm eligibility) | C63: M0021 | D63: Khormali A.; Ahmadi S.; Kazemzadeh Y. | E63: Performance evaluation of hybrid polymer-phosphonate scale inhibitors in oilfield water flooding operations | F63: 2026 | G63: Petroleum Research | H63: 10.1016/j.ptlrs.2026.01.014 | I63: Scopus | J63: R | K63: 11 | L63: 11 | M63: Included — proceed to full-text
A64: 60 | B64: 2 - Relevant (confirm eligibility) | C64: M0270 | D64: Mady M.F.; Bayat P.; Kelland M.A. | E64: Environmentally Friendly Phosphonated Polyetheramine Scale Inhibitors - Excellent Calcium Compatibility for Oilfield Applications | F64: 2020 | G64: Industrial and Engineering Chemistry Research | H64: 10.1021/acs.iecr.0c01636 | I64: Scopus;WoS | J64: R | K64: 73 | L64: 10.43 | M64: Included — proceed to full-text
A65: 61 | B65: 2 - Relevant (confirm eligibility) | C65: M0110 | D65: Khodabakhshi M.J.; Bijani M. | E65: Predicting scale deposition in oil reservoirs using machine learning optimization algorithms | F65: 2024 | G65: Results in Engineering | H65: 10.1016/j.rineng.2024.102263 | I65: Scopus | J65: R | K65: 31 | L65: 10.33 | M65: Included — proceed to full-text
... A166: 162 | B166: 2 - Relevant (confirm eligibility) | C166: M0433 | D166: Jaho S.; Sygouni V.; Rokidi S.G.; Parthenios J.; Koutsoukos P.G.; Paraskeva C.A. | E166: Precipitation of Calcium Carbonate in Porous Media in the Presence of n-Dodecane | F166: 2016 | G166: Crystal Growth and Design | H166: 10.1021/acs.cgd.6b01048 | I166: Scopus;WoS | J166: R | K166: 19 | L166: 1.73 | M166: Included — proceed to full-text
A167: 163 | B167: 2 - Relevant (confirm eligibility) | C167: M0285 | D167: Ko S.; Wang X.; Zhao Y.; Dai C.; Lu Y.-T.; Deng G.; Paudyal S.; Mateen S.; Kan A.T.; Tomson M.B. | E167: Prevention of mineral scale deposition using dispersants and inhibitors | F167: 2020 | G167: Society of Petroleum Engineers - SPE International Oilfield Scale Conference and Exhibition, OSS 2020 | I167: Scopus | J167: R | K167: 12 | L167: 1.71 | M167: Included — proceed to full-text
A168: 164 | B168: 2 - Relevant (confirm eligibility) | C168: M0081 | D168: Koshani R.; Yeh S.-L.; Pitcher M.L.; Sheikhi A. | E168: Antiscaling Pickering Emulsions Enabled by Amphiphilic Hairy Cellulose Nanocrystals | F168: 2024 | G168: ACS Applied Materials and Interfaces | H168: 10.1021/acsami.4c03451 | I168: Scopus;WoS | J168: R | K168: 5 | L168: 1.67 | M168: Included — proceed to full-text
A169: 165 | B169: 2 - Relevant (confirm eligibility) | C169: M0117 | D169: Freitas, VMS; Paschoalino, WJ; Vieira, LCS; Silva, JM; Couto, BC; Gobbi, AL; Lima, RS | E169: Sensitive Monitoring of the Minimum Inhibitor Concentration under Real Inorganic Scaling Scenarios | F169: 2024 | G169: ACS OMEGA | H169: 10.1021/acsomega.4c04912 | I169: WoS | J169: R | K169: 5 | L169: 1.67 | M169: Included — proceed to full-text
A170: 166 | B170: 2 - Relevant (confirm eligibility) | C170: M0120 | D170: Zhao L.; Zhang Y.; He Y.; Yang Z.; Liang X.; Wang X.; Mao Q. | E170: Study on the Mechanism of Wellbore Blockage and Scaling Trend Prediction of Keshen Block | F170: 2024 | G170: Processes | H170: 10.3390/pr12040782 | I170: Scopus;WoS | J170: R | K170: 5 | L170: 1.67 | M170: Included — proceed to full-text
A171: 167 | B171: 2 - Relevant (confirm eligibility) | C171: M0211 | D171: Dai, ZY; Lu, YT; Kan, A; Leschied, C; Zhao, Y; Dai, C; Wang, X; Paudyal, S; Ko, S; Tomson, M | E171: A mechanistic software platform for mineral surface deposition and inhibition prediction under different flow conditions | F171: 2021 | G171: DESALINATION | H171: 10.1016/j.desal.2021.115071 | I171: WoS | J171: R | K171: 10 | L171: 1.67 | M171: Included — proceed to full-text
A172: 168 | B172: 2 - Relevant (confirm eligibility) | C172: M0357 | D172: Teixeira, TP; Salgado, CM; Dam, RSD; Salgado, WL | E172: Inorganic scale thickness prediction in oil pipelines by gamma-ray attenuation and artificial neural network | F172: 2018 | G172: APPLIED RADIATION AND ISOTOPES | H172: 10.1016/j.apradiso.2018.08.008 | I172: WoS | J172: R | K172: 15 | L172: 1.67 | M172: Included — proceed to full-text
A173: 169 | B173: 2 - Relevant (confirm eligibility) | C173: M0415 | D173: Al Nasser W.N.; Shah U.V.; Nikiforou K.; Petrou P.; Heng J.Y.Y. | E173: Effect of silica nanoparticles to prevent calcium carbonate scaling using an in situ turbidimetre | F173: 2016 | G173: Chemical Engineering Research and Design | H173: 10.1016/j.cherd.2015.12.006 | I173: Scopus;WoS | J173: R | K173: 18 | L173: 1.64 | M173: Included — proceed to full-text
A174: 170 | B174: 2 - Relevant (confirm eligibility) | C174: M0175 | D174: Ferreira B.X.; Barbosa C.R.H.; Cajaiba J.; Kartnaller V.; Santos B.F. | E174: Development of Artificial Neural Network Models for the Simulation of a CaCO3 Scale Formation Process in the Presence of Monoethylene Glycol (MEG) in Dynamic Tube Blocking Test Equipment | F174: 2022 | G174: Energy and Fuels | H174: 10.1021/acs.energyfuels.1c03364 | I174: Scopus;WoS | J174: R | K174: 8 | L174: 1.6 | M174: Included — proceed to full-text
A175: 171 | B175: 2 - Relevant (confirm eligibility) | C175: M0188 | D175: Gasimli N.; Mahmoud M.; Kamal M.S.; Patil S.; Alsaiari H.A.; Hussein I.A. | E175: Iron Sulfide Scale Inhibition in Carbonate Reservoirs | F175: 2022 | G175: ACS Omega | H175: 10.1021/acsomega.2c01568 | I175: Scopus;WoS | J175: R | K175: 8 | L175: 1.6 | M175: Included — proceed to full-text
A176: 172 | B176: 2 - Relevant (confirm eligibility) | C176: M0194 | D176: Ugoyah J.C.; Ajienka J.A.; Wachikwu-Elechi V.U.; Ikiensikimama S.S. | E176: Prediction of Scale Precipitation by Modelling its Thermodynamic Properties using Machine Learning Engineering | F176: 2022 | G176: Society of Petroleum Engineers - SPE Nigeria Annual International Conference and Exhibition, NAIC 2022 | H176: 10.2118/212010-MS | I176: Scopus | J176: R | K176: 8 | L176: 1.6 | M176: Included — proceed to full-text
A177: 173 | B177: 2 - Relevant (confirm eligibility) | C177: M0260 | D177: Ramstad K.; Sandengen K.; Mitchell A.F.; Moldrheim E. | E177: Correlating calcium carbonate scale risk with field experience data | F177: 2020 | G177: Society of Petroleum Engineers - SPE International Oilfield Scale Conference and Exhibition, OSS 2020 | I177: Scopus | J177: R | K177: 11 | L177: 1.57 | M177: Included — proceed to full-text
A178: 174 | B178: 2 - Relevant (confirm eligibility) | C178: M0459 | D178: Hany Gamal; Salaheldin Elkatatny; Dhafer Al Shehri; Mohamed Bahgat | E178: A Novel Low-Temperature Non-Corrosive Sulfate/Sulfide Scale Dissolver | F178: 2020 | G178: Sustainability | H178: 10.3390/su12062455 | I178: SDL | J178: R | K178: 11 | L178: 1.57 | M178: Included — proceed to full-text
A179: 175 | B179: 2 - Relevant (confirm eligibility) | C179: M0412 | D179: Khamis, E; El-Rafey, E; Gaber, AMA; Hefnawy, A; El-Din, NGES; Ahmed, MSEE | E179: Comparative study between green and red algae in the control of corrosion and deposition of scale in water systems | F179: 2016 | G179: DESALINATION AND WATER TREATMENT | H179: 10.1080/19443994.2015.1135480 | I179: WoS | J179: R | K179: 17 | L179: 1.55 | M179: Included — proceed to full-text
A180: 176 | B180: 2 - Relevant (confirm eligibility) | C180: M0045 | D180: Kalantari Meybodi M.; Sorbie K.S.; Vazquez O.; Mackay E.J. | E180: An integrated model of scale inhibitor (DETPMP) transport, coupled adsorption/precipitation (Γ/Π) and reaction in carbonate systems | F180: 2025 | G180: Advances in Water Resources | H180: 10.1016/j.advwatres.2025.105042 | I180: Scopus;WoS | J180: R | K180: 3 | L180: 1.5 | M180: Included — proceed to full-text
A181: 177 | B181: 2 - Relevant (confirm eligibility) | C181: M0048 | D181: Karaly A.H.; Kelland M.A.; Mady M.F. | E181: Branched Phosphonated Polyetheramine-Coated Magnetic Nanoparticles for Enhanced Oilfield Scale Management | F181: 2025 | G181: ACS Applied Polymer Materials | H181: 10.1021/acsapm.5c02130 | I181: Scopus;WoS | J181: R | K181: 3 | L181: 1.5 | M181: Included — proceed to full-text
A182: 178 | B182: 2 - Relevant (confirm eligibility) | C182: M0079 | D182: Abbasi P.; Madani M.; Abbasi S. | E182: Treatment of water disposal injection process by oilfield chemicals: Maintaining injectivity and environmental effects | F182: 2025 | G182: Petroleum Research | H182: 10.1016/j.ptlrs.2025.04.007 | I182: Scopus | J182: R | K182: 3 | L182: 1.5 | M182: Included — proceed to full-text
A183: 179 | B183: 2 - Relevant (confirm eligibility) | C183: M0137 | D183: Alotaibi F.; Almubarak T.; Alhamad L.; Al Moajil A. | E183: Chelating Chemicals: A Solution to End the Battle with Calcium Sulfate Scale | F183: 2023 | G183: SPE Middle East Oil and Gas Show and Conference, MEOS, Proceedings | H183: 10.2118/213502-MS | I183: Scopus | J183: R | K183: 6 | L183: 1.5 | M183: Included — proceed to full-text
A184: 180 | B184: 2 - Relevant (confirm eligibility) | C184: M0212 | D184: Shajari M.; Rashidi F. | E184: A new coupled model for permeability-impairment prediction because of mineral scale deposition in water-injection wells | F184: 2021 | G184: SPE Reservoir Evaluation and Engineering | H184: 10.2118/202476-PA | I184: Scopus;WoS | J184: R | K184: 9 | L184: 1.5 | M184: Included — proceed to full-text
A185: 181 | B185: 2 - Relevant (confirm eligibility) | C185: M0228 | D185: Li, QY; Wang, LJ; Perzan, Z; Caers, J; Brown, GE Jr; Bargar, JR; Maher, K | E185: Global Sensitivity Analysis of a Reactive Transport Model for Mineral Scale Formation During Hydraulic Fracturing | F185: 2021 | G185: ENVIRONMENTAL ENGINEERING SCIENCE | H185: 10.1089/ees.2020.0365 | I185: WoS | J185: R | K185: 9 | L185: 1.5 | M185: Included — proceed to full-text
A186: 182 | B186: 2 - Relevant (confirm eligibility) | C186: M0267 | D186: Rodrigues H.; Mackay E.; Arnold D.; Azari V.; Vazquez O. | E186: Economic optimization and calcite scale management of CO2-EOR in carbonate reservoirs | F186: 2020 | G186: Society of Petroleum Engineers - SPE International Oilfield Scale Conference and Exhibition, OSS 2020 | I186: Scopus | J186: R | K186: 10 | L186: 1.43 | M186: Included — proceed to full-text
A187: 183 | B187: 2 - Relevant (confirm eligibility) | C187: M0287 | D187: Chen T.; Wang Q.; Chang F.; Aljeaban N.; Alnoaimi K. | E187: Recent development and remaining challenges of iron sulfide scale mitigation in sour-gas wells | F187: 2020 | G187: SPE Production and Operations | H187: 10.2118/199365-PA | I187: Scopus;WoS | J187: R | K187: 10 | L187: 1.43 | M187: Included — proceed to full-text
A188: 184 | B188: 2 - Relevant (confirm eligibility) | C188: M0385 | D188: Wylde J.J.; Turner N.; Austill M.; Okocha C.; Obeyesekere N. | E188: Development, testing and field application of a novel combination foamer-iron sulfide scale inhibitor-corrosion inhibitor in east Texas | F188: 2017 | G188: Proceedings - SPE International Symposium on Oilfield Chemistry | H188: 10.2118/184584-ms | I188: Scopus | J188: R | K188: 14 | L188: 1.4 | M188: Included — proceed to full-text
A189: 185 | B189: 2 - Relevant (confirm eligibility) | C189: M0309 | D189: Zhang, P; Liu, Y; Kuok, SC; Kan, AT; Tomson, MB | E189: Development of modeling approaches to describe mineral scale deposition kinetics in porous medium and pipe flow system | F189: 2019 | G189: JOURNAL OF PETROLEUM SCIENCE AND ENGINEERING | H189: 10.1016/j.petrol.2019.03.070 | I189: WoS | J189: R | K189: 11 | L189: 1.38 | M189: Included — proceed to full-text
A190: 186 | B190: 2 - Relevant (confirm eligibility) | C190: M0314 | D190: de Souza, AVA; Rosário, F; Cajaiba, J | E190: Evaluation of Calcium Carbonate Inhibitors Using Sintered Metal Filter in a Pressurized Dynamic System | F190: 2019 | G190: MATERIALS | H190: 10.3390/ma12111849 | I190: WoS | J190: R | K190: 11 | L190: 1.38 | M190: Included — proceed to full-text
A191: 187 | B191: 2 - Relevant (confirm eligibility) | C191: M0414 | D191: Bhandari N.; Kan A.T.; Dai Z.; Zhang F.; Yan F.; Ruan G.G.; Alsaiari H.A.; Zhang Z.; Liu Y.; Lu Y.; Deng G.; Tomson M.B. | E191: Effect of hydrodynamic pressure on mineral precipitation kinetics and scaling risk at HPHT | F191: 2016 | G191: Society of Petroleum Engineers - SPE International Oilfield Scale Conference and Exhibition | H191: 10.2118/179873-ms | I191: Scopus | J191: R | K191: 15 | L191: 1.36 | M191: Included — proceed to full-text
A192: 188 | B192: 2 - Relevant (confirm eligibility) | C192: M0422 | D192: Goodwin N.; Graham G.M.; Frigo D.M.; Kremer E. | E192: Halite deposition - Prediction and laboratory evaluation | F192: 2016 | G192: Society of Petroleum Engineers - SPE International Oilfield Scale Conference and Exhibition | H192: 10.2118/179861-ms | I192: Scopus | J192: R | K192: 15 | L192: 1.36 | M192: Included — proceed to full-text
A193: 189 | B193: 2 - Relevant (confirm eligibility) | C193: M0094 | D193: Oliveira J.; Ortiz R.W.P.; Passos N.S.; Venancio F.; Gonçalves V.O.O.; Cajaiba J.; Ribeiro-Santos R.; Perrone D.; Kartnaller V. | E193: Evaluating starchy food effluents as potential green inhibitors of calcium carbonate scale in oil and gas production | F193: 2024 | G193: Brazilian Journal of Chemical Engineering | H193: 10.1007/s43153-023-00404-0 | I193: Scopus;WoS | J193: R | K193: 4 | L193: 1.33 | M193: Included — proceed to full-text
A194: 190 | B194: 2 - Relevant (confirm eligibility) | C194: M0102 | D194: Murtaza M.; Budiman O.; Kamal M.S.; Alajmi S.N.; Al-Jawad M.; Mahmoud M. | E194: Ionic Liquid-Based Formulation for Inhibiting Calcium Sulfate Scale in High-Pressure High-Temperature Wells | F194: 2024 | G194: Society of Petroleum Engineers - ADIPEC 2024 | H194: 10.2118/222368-MS | I194: Scopus | J194: R | K194: 4 | L194: 1.33 | M194: Included — proceed to full-text
A195: 191 | B195: 2 - Relevant (confirm eligibility) | C195: M0103 | D195: Chen S.; Aljeaban N.A.; Chen T.; Huang T. | E195: Laboratory Synthesis and Evaluation of Phosphorous-Tagged Polymeric Scale Inhibitors | F195: 2024 | G195: Society of Petroleum Engineers - SPE Conference at Oman Petroleum and Energy Show, OPES 2024 | H195: 10.2118/218604-MS | I195: Scopus | J195: R | K195: 4 | L195: 1.33 | M195: Included — proceed to full-text
A196: 192 | B196: 2 - Relevant (confirm eligibility) | C196: M0119 | D196: Lobo J.S.; Serpa F.S.; Filho E.B.M.; Castro B.B.; Borges G.R.; Dariva C.; Franceschi E. | E196: Study of the kinetic behavior of chemical inhibitors in calcium carbonate scale formation | F196: 2024 | G196: Brazilian Journal of Chemical Engineering | H196: 10.1007/s43153-023-00328-9 | I196: Scopus;WoS | J196: R | K196: 4 | L196: 1.33 | M196: Included — proceed to full-text
A197: 193 | B197: 2 - Relevant (confirm eligibility) | C197: M0125 | D197: El-Sawaf A.K.; Mubarak M.F.; Selim H.; Hosny R. | E197: Synthesis and evaluation of novel copper hydroxide-loaded SBA-15 as inhibitors for an oilfield carbonate scale control: an experiment and a model study | F197: 2024 | G197: H2Open Journal | H197: 10.2166/h2oj.2023.076 | I197: Scopus | J197: R | K197: 4 | L197: 1.33 | M197: Included — proceed to full-text
A198: 194 | B198: 2 - Relevant (confirm eligibility) | C198: M0126 | D198: Hashemi S.H.; Besharati Z.; Torabi F.; Pimentel N. | E198: Thermodynamic Prediction of Scale Formation in Oil Fields During Water Injection: Application of SPsim Program Through Utilizing Advanced Visual Basic Excel Tool | F198: 2024 | G198: Processes | H198: 10.3390/pr12122722 | I198: Scopus;WoS | J198: R | K198: 4 | L198: 1.33 | M198: Included — proceed to full-text
... A201: 197 | B201: 2 - Relevant (confirm eligibility) | C201: M0364 | D201: Wang W.; Wei W.; Ferrier N.; Arismendi N. | E201: Scale formation and inhibition study for water injection wells | F201: 2018 | G201: Society of Petroleum Engineers - SPE International Oilfield Scale Conference and Exhibition 2018 | H201: 10.2118/190732-ms | I201: Scopus | J201: R | K201: 12 | L201: 1.33 | M201: Included — proceed to full-text
A202: 198 | B202: 2 - Relevant (confirm eligibility) | C202: M0265 | D202: Paudyal S.; Mateen S.; Dai C.; Ko S.; Wang X.; Deng G.; Lu A.; Zhao Y.; Bingjie O.; Kan A.T.; Tomson M.B. | E202: Developments on calcium sulfate scaling prediction and control in oil and gas production | F202: 2020 | G202: Society of Petroleum Engineers - SPE International Oilfield Scale Conference and Exhibition, OSS 2020 | I202: Scopus | J202: R | K202: 9 | L202: 1.29 | M202: Included — proceed to full-text
A203: 199 | B203: 2 - Relevant (confirm eligibility) | C203: M0135 | D203: Wang X.; Li W.; Ye Y.; Navarathna C.; Reiss A.; Yao X.; Leschied C.; Shen Y.-Y.R.; Pimentel D.; Kan A.; Tomson M. | E203: Carbonate and Sulfide Mixed Scale: Corrosion, Prediction and Control | F203: 2023 | G203: Proceedings - SPE International Symposium on Oilfield Chemistry | H203: 10.2118/213780-MS | I203: Scopus | J203: R | K203: 5 | L203: 1.25 | M203: Included — proceed to full-text
A204: 200 | B204: 2 - Relevant (confirm eligibility) | C204: M0160 | D204: Dilsiz E.A.; Mihcakan I.M. | E204: The effects of calcium carbonate precipitation on high-velocity flow behavior in 3D printed fracture models | F204: 2023 | G204: Journal of Petroleum Science and Engineering | H204: 10.1016/j.petrol.2022.111264 | I204: Scopus;WoS | J204: R | K204: 5 | L204: 1.25 | M204: Included — proceed to full-text
A205: 201 | B205: 2 - Relevant (confirm eligibility) | C205: M0359 | D205: Khormali A.; Sharifov A.R.; Torba D.I. | E205: Investigation of barium sulfate precipitation and prevention using different scale inhibitors under reservoir conditions | F205: 2018 | G205: International Journal of Engineering, Transactions A: Basics | H205: 10.5829/ije.2018.31.10a.24 | I205: Scopus | J205: R | K205: 11 | L205: 1.22 | M205: Included — proceed to full-text
A206: 202 | B206: 2 - Relevant (confirm eligibility) | C206: M0453 | D206: Oscar Vazquez; Gill Ross; Myles M. Jordan; Dionysius Angga Baskoro; Eric Mackay; Clare Johnston; Alistair Strachan | E206: Automatic Optimization of Oilfield-Scale-Inhibitor Squeeze Treatments Delivered by Diving-Support Vessel | F206: 2018 | G206: SPE Journal | H206: 10.2118/184535-pa | I206: SDL | J206: R | K206: 11 | L206: 1.22 | M206: Included — proceed to full-text
A207: 203 | B207: 2 - Relevant (confirm eligibility) | C207: M0171 | D207: Dam, RSD; Salgado, WL; Schirru, R; Salgado, CM | E207: Application of deep neural network and gamma-ray scattering in eccentric scale calculation regardless of the fluids volume fraction inside a pipeline | F207: 2022 | G207: APPLIED RADIATION AND ISOTOPES | H207: 10.1016/j.apradiso.2022.110353 | I207: WoS | J207: R | K207: 6 | L207: 1.2 | M207: Included — proceed to full-text
A208: 204 | B208: 2 - Relevant (confirm eligibility) | C208: M0180 | D208: Aldeia W.; França G.P.; Miliotti M.A.; Martins A.L.; Schluter H.E.P.; Castro B.B.; Pereira A.Z.I.; Freitas T.C. | E208: Experimental Study of the Effect of Magnetic Field Associated with Inhibitor in Calcium Carbonate Scale Formation | F208: 2022 | G208: Society of Petroleum Engineers - SPE International Oilfield Scale Conference and Exhibition, OSS 2022 | H208: 10.2118/209488-MS | I208: Scopus | J208: R | K208: 6 | L208: 1.2 | M208: Included — proceed to full-text
A209: 205 | B209: 2 - Relevant (confirm eligibility) | C209: M0322 | D209: Sun, NN; Jiang, HY; Liang, AG; Zhang, DZ; Cai, HH; Zhang, LX; Chong, XM | E209: Influences of material types on the mechanisms of crystal growth in an aggregate scaling device | F209: 2019 | G209: INTERNATIONAL COMMUNICATIONS IN HEAT AND MASS TRANSFER | H209: 10.1016/j.icheatmasstransfer.2019.104303 | I209: WoS | J209: R | K209: 9 | L209: 1.12 | M209: Included — proceed to full-text
A210: 206 | B210: 2 - Relevant (confirm eligibility) | C210: M0349 | D210: Sorbie K.S.; Stamatiou A. | E210: Analytical Solutions of a One-Dimensional Linear Model Describing Scale Inhibitor Precipitation Treatments | F210: 2018 | G210: Transport in Porous Media | H210: 10.1007/s11242-018-1040-3 | I210: Scopus;WoS | J210: R | K210: 10 | L210: 1.11 | M210: Included — proceed to full-text
A211: 207 | B211: 2 - Relevant (confirm eligibility) | C211: M0353 | D211: Maffra D.A.; Freitas T.C.; Da Cruz G.F.; De Siqueira F.D.; Do Rosário F.F. | E211: Evaluation of barium sulfate scale inhibition using relative permeability modifier polymers as adsorption enhancer for mature offshore well treatments in Campos Basin, Brazil | F211: 2018 | G211: Industrial and Engineering Chemistry Research | H211: 10.1021/acs.iecr.8b01828 | I211: Scopus | J211: R | K211: 10 | L211: 1.11 | M211: Included — proceed to full-text
A212: 208 | B212: 2 - Relevant (confirm eligibility) | C212: M0371 | D212: Venancio F.; Rosário F.F.; Cajaiba J. | E212: Use of a dynamic system and reflectance measurements to assess the impact of monoethylene glycol on calcium carbonate scale | F212: 2018 | G212: Journal of Petroleum Science and Engineering | H212: 10.1016/j.petrol.2018.02.064 | I212: Scopus;WoS | J212: R | K212: 10 | L212: 1.11 | M212: Included — proceed to full-text
A213: 209 | B213: 2 - Relevant (confirm eligibility) | C213: M0381 | D213: Zhang F.; Hinrichsen C.J.; Kan A.T.; Wang W.; Wei W.; Dai Z.; Yan F.; Liu Y.; Bhandari N.; Zhang Z.; Ruan G.; Tomson M.B. | E213: Calcium sulfate scaling risk and inhibition for a steamflood project | F213: 2017 | G213: SPE Journal | H213: 10.2118/179875-pa | I213: Scopus;WoS | J213: R | K213: 11 | L213: 1.1 | M213: Included — proceed to full-text
A214: 210 | B214: 2 - Relevant (confirm eligibility) | C214: M0390 | D214: Bhandari N.; Ruan G.; Liu Y.; Zhang F.; Yan F.; Saiari H.A.; Zhang Z.; Dai Z.; Lu Y.; Deng G.; Kan A.T.; Tomson M.B. | E214: Identification of new chemical formulation for control of metal sulfides FeS, ZnS and PbS scale deposition | F214: 2017 | G214: Proceedings - SPE International Symposium on Oilfield Chemistry | H214: 10.2118/184526-ms | I214: Scopus | J214: R | K214: 11 | L214: 1.1 | M214: Included — proceed to full-text
... A234: 230 | B234: 2 - Relevant (confirm eligibility) | C234: M0249 | D234: Adegoke S.O.; Falode O.A.; Nwankwo P.C. | E234: Understanding oilfield scale deposition and inhibition mechanisms for optimum management: A review | F234: 2021 | G234: Society of Petroleum Engineers - SPE Nigeria Annual International Conference and Exhibition 2021, NAIC 2021 | H234: 10.2118/207133-MS | I234: Scopus | J234: R | K234: 6 | L234: 1 | M234: Included — proceed to full-text
A235: 231 | B235: 2 - Relevant (confirm eligibility) | C235: M0266 | D235: Lu A.Y.-T.; Paudyal S.; Ko S.; Dai C.; Ouyang B.; Deng G.; Zhao Y.; Wang X.; Mateen S.; Liu H.; Yo T.; Kan A.; Tomson M. | E235: Does barite scale deposit at a kinetic stable flow? | F235: 2020 | G235: Society of Petroleum Engineers - SPE International Oilfield Scale Conference and Exhibition, OSS 2020 | I235: Scopus | J235: R | K235: 7 | L235: 1 | M235: Included — proceed to full-text
A236: 232 | B236: 2 - Relevant (confirm eligibility) | C236: M0295 | D236: Mpelwa M.; Tang S.; Jin L. | E236: The study on multifunctional aminoalkylenephosphonate-based antiscalant for industrial water systems under harsh conditions | F236: 2020 | G236: International Journal of Industrial Chemistry | H236: 10.1007/s40090-020-00208-y | I236: Scopus | J236: R | K236: 7 | L236: 1 | M236: Included — proceed to full-text
...
